Workbook

Sheet Key Ach. 
A1: # | B1: Project / Area | C1: Project Type | D1: Key Achievement
A2: 1 | B2: Sparta CRM | C2: In-house Project | D2: Delivered a stable release of the Sparta CRM with improved reliability and smooth operations.
A3: 2 | B3: Workgrid Enhancement | C3: In-house Project | D3: Developed and implemented the Sprint Module to enhance project and sprint management.
A4: 3 | B4: Sharooq’s Project, NWT, Nomads, Briggs, Footwear, Catesby, etc. | C4: Client Project | D4: Ensured project stability and smooth deliveries with proper CR tracking, documentation, and timely implementation.
A5: 4 | B5: FastRanking Website | C5: In-house Project | D5: Successfully developed the next-generation FastRanking website with a modern and improved solution.
A6: 5 | B6: Vee Repairs Website | C6: In-house Project | D6: Developed the next-generation Vee Repairs website with a modern and improved architecture.
A7: 6 | B7: Rabia, Sofiya, Jeleel, etc. | C7: Client Project | D7: Delivered client projects on time and maintained strong client satisfaction, reflected through 5-star Google reviews and positive feedback.
A8: 7 | B8: Client Retention & Payment Recovery | C8: Client Project | D8: Successfully retained 6 previously pending clients, strengthened relationships, delivered requirements on time, and recovered outstanding payments.
A9: 8 | B9: Sprint Retrospective & Project Management Tools | C9: In-house Project | D9: Created a Sprint Retrospective tool for management reporting and contributed to developing a next-generation project management tool for detailed project, employee, and sprint tracking.
A10: 9 | B10: Superhouse Education Foundation | C10: Client Project | D10: Successfully recovered the pending £1,000 AMC payment that had been outstanding for 2 months.
A11: 10 | B11: Client Onboarding Support | C11: Client Project | D11: Supported agents with client questionnaires and quick onboarding questions to streamline the client onboarding process.

Sheet New Projects_July
A1: Project Management Dashboard
A3: Total Projects | D3: New Projects | F3: Old Projects | H3: In-Progress | J3: Done | L3: On-Hold | N3: Backoff
A4: 28 | D4: 21 | F4: 7 | H4: 14 | J4: 9 | L4: 3 | N4: 1
D5: Total Cost | F5: Invoice Value | H5: Collected | J5: Pending | L5: Collection %
D6: =SUMPRODUCT((D34:D62<>"BackedOff")*VALUE(SUBSTITUTE(SUBSTITUTE(H34:H62,"£",""),",",""))) -> 14214.33 | F6: =SUMPRODUCT((D34:D62<>"BackedOff")*VALUE(SUBSTITUTE(SUBSTITUTE(I34:I62,"£",""),",",""))) -> 16124.8 | H6: NA | J6: NA | L6: NA
A31: Newly Added Projects
A33: Project Type | B33: Client Name | C33: Project Name | D33: Current Status | E33: Service | F33: Onboarding Date | G33: Deadline | H33: Project Cost | I33: Inc VAT (Invoice Value) | J33: Payment Frequence | K33: Collected Amount | L33: Amount Pending | M33: Comments
A34: New | B34: Reading Properties Group LTD | C34: Reading Properties Group LTD | D34: In-Progress | E34: Web Development | F34: 16th June,2026 | H34: £ 4,000.00 | I34: £ 4,000.00 | J34: NA | K34: Not Keeping Track of the Invoices. Discussed with Accounts.& Reporting Manager | L34: NA | M34: RPG Done, RDS : 80% & RF : 50%
A35: New | B35: Aspire Learning LTD | C35: Aspire Learning LTD | D35: In-Progress | E35: Web Development | H35: £ 333.33 | I35: £ 400.00 | J35: NA | K35: Not Keeping Track of the Invoices. Discussed with Accounts.& Reporting Manager | L35: NA | M35: Content Pending from Client End
A36: New | B36: GoldFinch Insulations LTD | C36: GoldFinch Insulations LTD | D36: Done | E36: Web Development | F36: 17th July,2026 | G36: 27th July,2026 | H36: £ 200.00 | I36: £ 240.00 | J36: NA | K36: Not Keeping Track of the Invoices. Discussed with Accounts.& Reporting Manager | L36: NA | M36: Done
A37: New | B37: De'osa Engg. LTD | C37: De'osa Engg. LTD | D37: On-Hold | E37: Web Development | H37: £ 400.00 | I37: £ 480.00 | J37: NA | K37: Not Keeping Track of the Invoices. Discussed with Accounts.& Reporting Manager | L37: NA | M37: Client not responding , Demo Submitted
A38: New | B38: Malvern Renovation | C38: Malvern Renovation | D38: BackedOff | E38: Web Development | H38: £ 400.00 | I38: £ 480.00 | J38: NA | K38: Not Keeping Track of the Invoices. Discussed with Accounts.& Reporting Manager | L38: NA | M38: NA
A39: New | B39: PAV'S Driving School | C39: PAV'S Driving School | D39: Done | E39: Web Development | F39: 29th July,2026 | G39: 3rd Aug,2026 | H39: £ 100.00 | I39: £ 120.00 | J39: NA | K39: Not Keeping Track of the Invoices. Discussed with Accounts.& Reporting Manager | L39: NA | M39: Done
A40: New | B40: 88 Driving School | C40: 88 Driving School | D40: Done | E40: Web Development | F40: 31st July,2026 | G40: 26th Sep,2026 | H40: £ 300.00 | I40: £ 360.00 | J40: NA | K40: Not Keeping Track of the Invoices. Discussed with Accounts.& Reporting Manager | L40: NA | M40: Done
A41: New | B41: Richmond Toto Professional Cleaning Ltd | C41: Richmond Toto Professional Cleaning Ltd | D41: Done | E41: Web Development | F41: 5th Aug,2026 | H41: £250.00 | I41: £300.00 | J41: NA | K41: Not Keeping Track of the Invoices. Discussed with Accounts.& Reporting Manager | L41: NA | M41: Done
A42: New | B42: Footwear Depot | C42: Footwear Depot | D42: In-Progress | E42: Web Development | H42: £499.00 | I42: £598.00 | J42: NA | K42: Not Keeping Track of the Invoices. Discussed with Accounts.& Reporting Manager | L42: NA | M42: In Progress , 80%
A43: New | B43: Briggs Industrial Footwear Limited | C43: Briggs Industrial Footwear Limited | D43: In-Progress | E43: Web Development | H43: £599.00 | I43: £718.80 | J43: NA | K43: Not Keeping Track of the Invoices. Discussed with Accounts.& Reporting Manager | L43: NA | M43: In Progress , 80%
A44: New | B44: Sofiya Designs Acedemy Ltd | C44: Sofiya Designs Acedemy Ltd | D44: Done | E44: Web Development | F44: 19th Aug,2026 | H44: £600.00 | I44: £720.00 | J44: NA | K44: Not Keeping Track of the Invoices. Discussed with Accounts.& Reporting Manager | L44: NA | M44: Done
A45: New | B45: Mountains Of Glory | C45: Mountains Of Glory | D45: On-Hold | E45: Web Development | H45: £416.00 | I45: £500.00 | J45: NA | K45: Not Keeping Track of the Invoices. Discussed with Accounts.& Reporting Manager | L45: NA | M45: NA
A46: New | B46: Spot Cleaners Ltd | C46: Spot Cleaners Ltd | D46: In-Progress | E46: Web Development | F46: 31st Aug,2026 | H46: £350.00 | I46: £420.00 | J46: NA | K46: Not Keeping Track of the Invoices. Discussed with Accounts.& Reporting Manager | L46: NA | M46: Testing is in progress
A47: New | B47: Sofiya Designs Ltd | C47: Sofiya Designs Ltd | D47: Done | E47: Web Development | F47: 02nd Sep,2026 | H47: £350.00 | I47: £420.00 | J47: NA | K47: Not Keeping Track of the Invoices. Discussed with Accounts.& Reporting Manager | L47: NA | M47: Done
A48: New | B48: Altai Mountain | C48: Altai Mountain | D48: In-Progress | E48: Web Development | F48: 14th Sep,2026 | G48: 8th Oct,2026 | H48: £300.00 | I48: £360.00 | J48: NA | K48: Not Keeping Track of the Invoices. Discussed with Accounts.& Reporting Manager | L48: NA | M48: Review pending from Client end.
A49: New | B49: Max Out Tutoring | C49: Max Out Tutoring | D49: In-Progress | E49: Web Development | F49: 15th Sep,2026 | G49: 9th Oct,2026 | H49: £500.00 | I49: £600.00 | J49: NA | K49: Not Keeping Track of the Invoices. Discussed with Accounts.& Reporting Manager | L49: NA | M49: Bug resolution
A50: New | B50: Optimum Global link Landing Page | C50: Optimum Global link Landing Page | D50: In-Progress | E50: Web Development | F50: 21th Sep, 2026 | G50: 29th Sep,2026 | H50: £100.00 | I50: £120.00 | J50: NA | K50: Not Keeping Track of the Invoices. Discussed with Accounts.& Reporting Manager | L50: NA | M50: Done
A51: New | B51: Burton Driving School | C51: Burton Driving School | D51: In-Progress | E51: Web Development | F51: 29th Sep, 2026 | H51: £250.00 | I51: £300.00 | J51: NA | K51: Not Keeping Track of the Invoices. Discussed with Accounts.& Reporting Manager | L51: NA | M51: Demo review pending from Client end
A52: New | B52: Party Supplys Ltd | C52: Party Supplys Ltd | D52: On-Hold | E52: Web Development | F52: 28th Sep,2026 | H52: £300.00 | I52: £360.00 | J52: NA | K52: Not Keeping Track of the Invoices. Discussed with Accounts.& Reporting Manager | L52: NA | M52: Assigned
A53: New | B53: Boiler Gas Tech Limited | C53: Boiler Gas Tech Limited | D53: To-Do | E53: Web Development | F53: 07th Oct, 2026 | H53: £333.00 | I53: £400.00 | J53: NA | K53: Not Keeping Track of the Invoices. Discussed with Accounts.& Reporting Manager | L53: NA | M53: Not Assigned
A54: New | B54: Connect Driving School Ltd | C54: Connect Driving School Ltd | D54: To-Do | E54: Web Development | F54: 06th Oct, 2026 | H54: £350.00 | I54: £420.00 | J54: NA | K54: Not Keeping Track of the Invoices. Discussed with Accounts.& Reporting Manager | L54: NA | M54: Not Assigned
A55: New | B55: UK Admission Manchester | C55: UK Admission Manchester | D55: To-Do | E55: Web Development | F55: 21st Oct, 2026 | H55: £200.00 | I55: £240.00 | J55: NA | K55: Not Keeping Track of the Invoices. Discussed with Accounts.& Reporting Manager | L55: NA | M55: Not Assigned
A56: Old | B56: Optimum Global Care | C56: Optimum Global Care | D56: Done | E56: Web Development | F56: NA | G56: 15th Sep,2026 | H56: £334.00 | I56: £400.00 | J56: NA | K56: Not Keeping Track of the Invoices. Discussed with Accounts.& Reporting Manager | L56: NA | M56: Done
A57: Old | B57: Corby Motors | C57: Corby Motors | D57: Done | E57: Web Development | F57: NA | H57: £750.00 | I57: £900.00 | J57: NA | K57: Not Keeping Track of the Invoices. Discussed with Accounts.& Reporting Manager | L57: NA | M57: Done
A58: Old | B58: Eagle Properties | C58: Eagle Properties | D58: In-Progress | E58: Web Development | F58: NA | H58: £450.00 | I58: £540.00 | J58: NA | K58: Not Keeping Track of the Invoices. Discussed with Accounts.& Reporting Manager | L58: NA | M58: Ready to go live
A59: Old | B59: Ace Learning Plus Limited | C59: Ace Learning Plus Limited | D59: Done | E59: Web Development | F59: NA | G59: 17th Sep,2026 | H59: £500.00 | I59: £599.00 | J59: NA | K59: Not Keeping Track of the Invoices. Discussed with Accounts.& Reporting Manager | L59: NA | M59: Done
A60: Old | B60: GreySon Studios | C60: GreySon Studios | D60: In-Progress | E60: Web Development | F60: NA | H60: £500.00 | I60: £599.00 | J60: NA | K60: Not Keeping Track of the Invoices. Discussed with Accounts.& Reporting Manager | L60: NA | M60: Ready to go live
A61: Old | B61: Stabilus Safety GmbH | C61: Stabilus Safety GmbH | D61: In-Progress | E61: Web Development | F61: 27th July, 2025 | H61: £650.00 | I61: £650.00 | J61: NA | K61: Not Keeping Track of the Invoices. Discussed with Accounts.& Reporting Manager | L61: NA | M61: UAT-SignOff Pending
A62: Old | B62: Varsity Music | C62: Varsity Music | D62: In-Progress | E62: Web Development | F62: 13th March, 2025 | H62: £300.00 | I62: £360.00 | J62: NA | K62: Not Keeping Track of the Invoices. Discussed with Accounts.& Reporting Manager | L62: NA | M62: Client not responding , Site is ready

Sheet AI Projects
A1: S.No. | B1: Project Name | C1: Customer | D1: Start Date | E1: Deadline | F1: Members | G1: Status | H1: Project Categories
A2: 1 | B2: Sparta Telecom - Data Management System [ DMA ] | C2: Sparta | D2: NA | E2: NA | F2: Shivam Backend Dev | G2: In Progress | H2: Inhouse
A3: 2 | B3: SEO Audit Tool — Real-Time Audit & AI Business Suggestions | C3: Sparta | D3: NA | E3: NA | F3: Shivam Backend Dev | G3: In Progress | H3: Inhouse
A4: 3 | B4: AI-Agent — TalkTalk Line Classification | C4: Sparta | D4: NA | E4: NA | F4: Shivam Backend Dev | G4: In Progress | H4: Inhouse
A5: 4 | B5: AI-Agent — Ameyo Voice Log Downloader | C5: Sparta | D5: NA | E5: NA | F5: Shivam Backend Dev | G5: In Progress | H5: Inhouse
A6: 6 | B6: VeeRepairs CRM — ETE Quality Automation | C6: Sparta | D6: NA | E6: NA | F6: Shivam Backend Dev | G6: In Progress | H6: Inhouse
A7: 7 | B7: AI Automation — Ameyo Call Details Report Downloader | C7: Sparta | D7: NA | E7: NA | F7: Shivam Backend Dev | G7: In Progress | H7: Inhouse
A8: 8 | B8: AI Agent - Call History Downloader — Ameyo | DMA Phase 3 | C8: Sparta | D8: NA | E8: NA | F8: Shivam Backend Dev | G8: In Progress | H8: Inhouse
A9: 9 | B9: FastRanking & VeeRepairs || QAAI — AI-Powered Quality Automation | C9: Sparta | D9: NA | E9: NA | F9: Shivam Backend Dev | G9: In Progress | H9: Inhouse
A10: 10 | B10: Hot Lead Automation | B2B Lead Generation | C10: Sparta | D10: NA | E10: NA | F10: Shivam Backend Dev | G10: In Progress | H10: Inhouse
A11: 11 | B11: HR - Sparta Recruit | AI-Powered Recruitment System | C11: Sparta | D11: NA | E11: NA | F11: Shivam Backend Dev | G11: In Progress | H11: Inhouse
A12: 12 | B12: Digital Marketing Hub | SEO Performance & Intelligence Platform | C12: Sparta | D12: NA | E12: NA | F12: Shivam Backend Dev | G12: UAT | H12: Inhouse
A13: 13 | B13: Backlink Checker Tool | Automated SEO Verification | C13: Sparta | D13: NA | E13: NA | F13: Shivam Backend Dev | G13: UAT | H13: Inhouse
... A19: 19.637363 | B19: QA-SAAS Platform | AI-Powered Quality Assurance | C19: Sparta | D19: NA | E19: NA | F19: Shivam Backend Dev | G19: TBD | H19: Inhouse

Sheet Sharooq & AllenHouse
A1: Project | B1: Task / Scope | C1: Status | D1: Category | E1: Work Hours
A2: Sharooq Projects
A3: Catesby England | B3: Redesign the website, add additional features and pages, and add new products. | C3: In Progress | D3: CR | E3: 6h
A4: Silver Street London | B4: Update product images (listed items), add new features and sections, and add new products. | C4: In Progress | D4: CR | E4: 4h
A5: Northwest Territory | B5: Update product images (listed items), change section placements, and add new products. | C5: Daily | D5: CR | E5: 4h
A6: Amen Shoes | B6: Redesign the website and add additional features and pages. | C6: In Progress | D6: CR | E6: 2h
A7: Marketplace Website | B7: Stock updates. | C7: Weekly | D7: AMC | E7: 2h
A8: Get Set Cook | B8: Design and create a new page and add new products. | C8: New CR | D8: CR | E8: 6h
A9: Nomads – Mimansa
A10: Nomads Clothing | B10: New CR - Product Upload | C10: N/A | D10: NA | E10: NA
A11: Nomads Trade (Wholesale) | B11: Removed the hidden feature, making all products visible to customers while keeping prices restricted to logged-in users. | C11: Done | D11: CR | E11: 6h
A14: Project | B14: Task / Scope ( 9th July, 26 ) | C14: Status | D14: Category | E14: Work Hours
A15: Sharooq Projects
A16: Catesby England | B16: Creating MEGA Menu | C16: In Progress | D16: CR | E16: 4h
A17: Silver Street London | B17: Update product images (listed items) | C17: In Progress | D17: CR | E17: 3h
A22: AllenHouse
A23: APS Websites | B23: Update the H1 tags, Slug , Blogs for all the 7 AllenHouse websites. | C23: In Progress | D23: CR | E23: 3h
A27: Requirement | B27: Type | C27: CR Required? | D27: Reason | E27: Work Hours
A28: Remove the date from all booking banners | B28: UI/Design Change | C28: ✅ Yes | D28: Existing design is being modified. | E28: 4h
A29: Add a new "Booking Type" field | B29: New Feature | C29: ✅ Yes | D29: Introduction of a new form field and workflow.
A30: Position the field below Email and above Booking Date | B30: UI/Layout Change | C30: ✅ Yes | D30: Changes the existing form structure.
A31: Add options: Individual, Small Group, Full Table | B31: Feature Enhancement | C31: ✅ Yes | D31: New booking categories affecting functionality.
A32: Change Booking Date to dropdown for Individual & Small Group | B32: Functional Change | C32: ✅ Yes | D32: Existing booking behaviour is being modified.
A33: Show calendar picker for Full Table | B33: Functional Change | C33: ✅ Yes | D33: New conditional functionality.
A34: Restrict Full Table bookings to 15+ days | B34: Business Logic | C34: ✅ Yes | D34: New validation/business rule.
A35: Allow existing Full Table events within 15 days to remain bookable | B35: Advanced Business Logic | C35: ✅ Yes | D35: Additional booking workflow and database logic.
A36: Send booking details to Gmail after submission | B36: Notification Feature | C36: ✅ Yes | D36: New email notification recipient/functionality.
A37: Send booking details to WhatsApp after submission | B37: Third-party Integration | C37: ✅ Yes | D37: New WhatsApp notification integration.

Sheet Client Projects
A1: S.No. | B1: Project Name | C1: Customer | D1: Start Date | E1: Deadline | F1: Members | G1: Status | H1: Project Categories | I1: Comments | J1: Contacts | K1: Status
A2: 1 | B2: FCL(firstclasslearning) | C2: FCL(firstclasslearning) | D2: 46158 | E2: 46174 | F2: Vipin, Avinash, Nikhil & Abhijeet | G2: Finished | H2: Wordpress | I2: Camping is live.
A3: 2 | B3: Surge Production | C3: Surge Production | D3: 46153 | E3: 46184 | F3: Deepak , Abhijeet | G3: UAT | H3: Wordpress | I3: Waiting for client response - UAT Pending from client side. | J3: info.surgeproductions@gmail.com | K3: Mail sent
A4: 3 | B4: Nomads Clothing | C4: Nomads Clothing | D4: 46156 | E4: 46186 | F4: NWNikhil Web Developer | G4: Finished | H4: Shopify | I4: Deployed Successfully, Taking followup from the client is everything is good at their side.
A5: 4 | B5: APS-CMS-MIGRATION | C5: Allen House | D5: 46167 | E5: 46189 | F5: Abhijeet , Vani , Suraj , Raunik & Nikhil | G5: Finished | H5: Custom | I5: Done
A6: 5 | B6: Varsity Audio Visuals | C6: Varsity Audio Visuals | D6: 46185 | E6: 46192 | F6: AWADAman Web Developer, Avinash Designer | G6: In Progress | H6: Wordpress | I6: In progress, team is working on homepage and once that is done team needs to test the same. | J6: <dhruv@varsityaudiovisuals.com><info@varsityaudiovisuals.com>
A7: 6 | B7: Eagle Properties | C7: Eagle Properties | D7: 46178 | E7: 46193 | F7: Deepak Web Developer | G7: In Progress | H7: Wordpress | I7: Need images from Avinash for the add-ons services, ETA : 29th June, 2026 | J7: kashif@eaglepropertycare.co.uk
A8: 7 | B8: FH Furniture | C8: FH Furniture | D8: 46073 | E8: 46183 | F8: Nikhil, Deepak & Abhijeet | G8: In Progress | H8: Shopify | I8: Need to follow-up regarding the client. | J8: faith.fhfurniture@gmail.com | K8: Mail sent
A9: 8 | B9: Landing Page Creation | C9: DrivewithGreta | D9: 46185 | E9: 46186 | F9: Deepak | G9: Finished | H9: Wordpress | I9: Done.
A10: 9 | B10: Briggs Safety Wear | C10: SEO - Briggs Safety Wear | D10: 27-March-2026 | E10: 15-April-2026 | F10: Aman | G10: Finished | H10: Wordpress | I10: Done
A11: 10 | B11: LAYLA GORDON | C11: LAYLA GORDON | D11: 28-March-2026 | E11: 15-April-2026 | F11: Aman | G11: Finished | H11: Wordpress | I11: Done
A12: 11 | B12: RBD Driving School | C12: RBD Driving School | D12: 02-April-2026 | E12: 15-April-2026 | F12: ASDWAbhijeet Singh Software Tester, Deepak Web Developer | G12: In Progress | H12: Shopify | I12: Demo Deployed, But no response from the client side
A13: 12 | B13: 4 Corners Cleaning Services Ltd | C13: 4 Corners Cleaning Services Ltd | D13: 24-February-2026 | E13: 15-April-2026 | F13: ASAbhijeet Singh Software Tester | G13: In Progress | H13: Wordpress | I13: No Response from Client | J13: red_scorpion5@hotmail.co.uk | K13: Mail sent
A14: 13 | B14: OBIsonic Digital Photography | C14: OBIsonic Digital Photography | D14: 12-February-2026 | E14: 15-April-2026 | F14: ASAbhijeet Singh Software Tester | G14: In Progress | H14: Wordpress | I14: No Response from Client | J14: contact@obisonicdp.co.uk | K14: Mail sent
A15: 14 | B15: Greyson Studios | C15: Mr. Matthew Elegbede | D15: 10-March-2026 | E15: 15-April-2026 | F15: DWDeepak Web Developer | G15: In Progress | H15: Wordpress | I15: Waiting for client response - Need to followup. | J15: matthewelegbede99@gmail.com | K15: Mail sent
A16: 15 | B16: JEWELLERY DESIGN CENTRE LIMITED | C16: JEWELLERY DESIGN CENTRE LIMITED | D16: 16-April-2026 | E16: 20-May-2026 | F16: DWAWDeepak Web Developer, Aman Web Developer | G16: Finished | H16: Shopify | I16: Done
A17: 16 | B17: NWT | C17: NWT | D17: 21-January-2026 | E17: 30-May-2026 | F17: Aman | G17: Finished | H17: Shopify | I17: Done
A18: 17 | B18: Jans Solutions Ltd | C18: Jans Solutions Ltd | D18: 24-February-2026 | E18: 30-May-2026 | F18: Aman | G18: Finished | H18: Wordpress | I18: Done
A19: 18 | B19: Nomads Saige | C19: Nomads Saige | D19: 02-April-2026 | E19: 05-June-2026 | F19: Aman | G19: Finished | H19: Shopify | I19: Done
A20: 19 | B20: Silver Street London | C20: Silver Street London | D20: 06-April-2026 | E20: 10-June-2026 | F20: Aman | G20: Finished | H20: Shopify | I20: Done
A21: 20 | B21: Varsity Audio Visuals | C21: Varsity Audio Visuals | D21: 12-June-2026 | E21: 19-June-2026 | F21: AWADAman Web Developer, Avinash Designer | G21: Finished | H21: Wordpress | I21: Done
A22: 21 | B22: AMEN SHOES | C22: AMEN SHOES | D22: 24-January-2026 | E22: 30-June-2026 | F22: Aman | G22: Finished | H22: Shopify | I22: Done
A23: 22 | B23: Allen Group - DPS | C23: Allen House | D23: 30-March-2026 | E23: 30-June-2026 | F23: Suraj, Raunik , Abhijeet & Vani | G23: Finished | H23: Custom | I23: Done
A24: 23 | B24: Allen House | C24: Allen House | D24: 01-March-2026 | E24: 22-July-2026 | F24: Suraj, Raunik , Abhijeet & Vani | G24: Finished | H24: Custom | I24: Done
A25: 24 | B25: Allen Group - Allenkids | C25: Allen House | D25: 30-March-2026 | E25: 31-July-2026 | F25: Suraj, Raunik , Abhijeet & Vani | G25: Finished | H25: Custom | I25: Done
A26: 25 | B26: READING PROPERTIES GROUP LTD | C26: Reading Properties Group | D26: 16-June-2026 | E26: 16-September-2026 | F26: Sandeep , Avinash , Abhijeet, Deepak & Aman | G26: TO-DO | H26: Wordpress | I26: In Progress
A27: 26 | B27: CATESBY ENGLAND | C27: CATESBY ENGLAND | D27: 21-January-2026 | E27: 31-July-2027 | F27: Aman & Nikhil | G27: Finished | H27: Shopify | I27: Done
A28: 27 | B28: Nomads Trade Website | C28: Nomads Trade Website | D28: 14-October-2025 | E28: 46203 | F28: Nikhil | G28: Finished | H28: Shopify | I28: Done
A29: 28 | B29: MARKETPLACE | C29: MARKETPLACE | D29: 21-January-2026 | E29: 46203 | F29: Aman | G29: Finished | H29: Shopify | I29: Done
A30: 29 | B30: Stabilus | C30: Stabilus | D30: 11-December-2025 | E30: 46203 | F30: ASAWAbhijeet Singh Software Tester, Aman Web Developer | G30: Finished | H30: Shopify | I30: Done
A31: 30 | B31: FOOTWEAR DEPOT - 1 | C31: FOOTWEAR DEPOT - 1 | D31: =VLOOKUP($B$31,Sheet1!$B$1:$I$74,4,0) -> 11-February-2026 | E31: =VLOOKUP($B$31,Sheet1!$B$1:$I$74,5,0) -> 13-February-2026 | F31: =VLOOKUP($B$31,Sheet1!$B$1:$I$74,6,0) -> AWNWAman Web Developer, Nikhil Web Developer | G31: Finished | H31: =VLOOKUP(B:B,Sheet1!$B$1:$I$74,8,0) -> Shopify | I31: Done
A32: 31 | B32: EA Driving School | C32: EA Driving School | D32: =VLOOKUP($B$32,Sheet1!$B$1:$I$74,4,0) -> 27-October-2025 | E32: =VLOOKUP(B:B,Sheet1!$B$1:$I$74,5,0) -> 09-April-2026 | F32: =VLOOKUP(B:B,Sheet1!$B$1:$I$74,6,0) -> ASAbhijeet Singh Software Tester | G32: Finished | H32: =VLOOKUP(B:B,Sheet1!$B$1:$I$74,8,0) -> Wordpress | I32: Done
A33: 32 | B33: RRJ Design | C33: RRJ Design | D33: =VLOOKUP($B$33,Sheet1!$B$1:$I$74,4,0) -> 24-February-2026 | E33: =VLOOKUP(B:B,Sheet1!$B$1:$I$74,5,0) -> 09-April-2026 | F33: =VLOOKUP(B:B,Sheet1!$B$1:$I$74,6,0) -> ASDWAbhijeet Singh Software Tester, Deepak Web Developer | G33: Finished | H33: =VLOOKUP(B:B,Sheet1!$B$1:$I$74,8,0) -> Wordpress | I33: Done
A34: 33 | B34: Agid Van | C34: Agid Van | D34: =VLOOKUP(B:B,Sheet1!$B$1:$I$74,4,0) -> 03-October-2025 | E34: =VLOOKUP(B:B,Sheet1!$B$1:$I$74,5,0) -> 13-April-2026 | F34: =VLOOKUP(B:B,Sheet1!$B$1:$I$74,6,0) -> ASAWAbhijeet Singh Software Tester, Aman Web Developer | G34: Finished | H34: =VLOOKUP(B:B,Sheet1!$B$1:$I$74,8,0) -> Wordpress | I34: Done
A35: 34 | B35: ACE LEARNING PLUS | C35: ACE LEARNING PLUS | D35: =VLOOKUP(B:B,Sheet1!$B$1:$I$74,4,0) -> 02-March-2026 | E35: =VLOOKUP(B:B,Sheet1!$B$1:$I$74,5,0) -> 15-April-2026 | F35: =VLOOKUP(B:B,Sheet1!$B$1:$I$74,6,0) -> AWASAman Web Developer, Abhijeet Singh Software Tester | G35: Finished | H35: =VLOOKUP(B:B,Sheet1!$B$1:$I$74,8,0) -> Wordpress | I35: Done
A36: 35 | B36: Boiler Gas Tech | C36: Boiler Gas Tech | D36: =VLOOKUP(B:B,Sheet1!$B$1:$I$74,4,0) -> 07-October-2025 | E36: =VLOOKUP(B:B,Sheet1!$B$1:$I$74,5,0) -> 15-April-2026 | F36: =VLOOKUP(B:B,Sheet1!$B$1:$I$74,6,0) -> +1 | G36: Finished | H36: =VLOOKUP(B:B,Sheet1!$B$1:$I$74,8,0) -> Wordpress | I36: Done
A37: 36 | B37: Julian Taxi | C37: Julian Taxi | D37: =VLOOKUP(B:B,Sheet1!$B$1:$I$74,4,0) -> 16-October-2025 | E37: =VLOOKUP(B:B,Sheet1!$B$1:$I$74,5,0) -> 15-April-2026 | F37: =VLOOKUP(B:B,Sheet1!$B$1:$I$74,6,0) -> ASAbhijeet Singh Software Tester | G37: Finished | H37: =VLOOKUP(B:B,Sheet1!$B$1:$I$74,8,0) -> Wordpress | I37: Done
A38: 37 | B38: Auto Market Place | C38: Auto Market Place | D38: =VLOOKUP(B:B,Sheet1!$B$1:$I$74,4,0) -> 29-November-2025 | E38: =VLOOKUP(B:B,Sheet1!$B$1:$I$74,5,0) -> 15-April-2026 | F38: =VLOOKUP(B:B,Sheet1!$B$1:$I$74,6,0) -> DWNWDeepak Web Developer, Nikhil Web Developer | G38: Finished | H38: =VLOOKUP(B:B,Sheet1!$B$1:$I$74,8,0) -> Wordpress | I38: Done
A39: 38 | B39: Dialogue Fosters | C39: Dialogue Fosters | D39: =VLOOKUP(B:B,Sheet1!$B$1:$I$74,4,0) -> 14-October-2025 | E39: =VLOOKUP(B:B,Sheet1!$B$1:$I$74,5,0) -> 15-April-2026 | F39: =VLOOKUP(B:B,Sheet1!$B$1:$I$74,6,0) -> AWAman Web Developer | G39: Finished | H39: =VLOOKUP(B:B,Sheet1!$B$1:$I$74,8,0) -> Wordpress | I39: Done
A40: 39 | B40: Wood and Home 99 Location pages | C40: Wood and Home 99 Location pages | D40: =VLOOKUP(B:B,Sheet1!$B$1:$I$74,4,0) -> 22-October-2025 | E40: =VLOOKUP(B:B,Sheet1!$B$1:$I$74,5,0) -> 15-April-2026 | F40: =VLOOKUP(B:B,Sheet1!$B$1:$I$74,6,0) -> ASAbhijeet Singh Software Tester | G40: Finished | H40: =VLOOKUP(B:B,Sheet1!$B$1:$I$74,8,0) -> Wordpress | I40: Done
A41: 40 | B41: Veedux Production | C41: Veedux Production | D41: =VLOOKUP(B:B,Sheet1!$B$1:$I$74,4,0) -> 25-October-2025 | E41: =VLOOKUP(B:B,Sheet1!$B$1:$I$74,5,0) -> 15-April-2026 | F41: =VLOOKUP(B:B,Sheet1!$B$1:$I$74,6,0) -> ASAbhijeet Singh Software Tester | G41: Finished | H41: =VLOOKUP(B:B,Sheet1!$B$1:$I$74,8,0) -> Wordpress | I41: Done
A42: 41 | B42: Eden's Edge | C42: Eden's Edge | D42: =VLOOKUP(B:B,Sheet1!$B$1:$I$74,4,0) -> 16-February-2026 | E42: =VLOOKUP(B:B,Sheet1!$B$1:$I$74,5,0) -> 15-April-2026 | F42: =VLOOKUP(B:B,Sheet1!$B$1:$I$74,6,0) -> 0 | G42: Finished | H42: =VLOOKUP(B:B,Sheet1!$B$1:$I$74,8,0) -> Wordpress | I42: Done
A43: 42 | B43: Kitchen 3D Limited | C43: Kitchen 3D Limited | D43: =VLOOKUP(B:B,Sheet1!$B$1:$I$74,4,0) -> 17-December-2025 | E43: =VLOOKUP(B:B,Sheet1!$B$1:$I$74,5,0) -> 15-April-2026 | F43: =VLOOKUP(B:B,Sheet1!$B$1:$I$74,6,0) -> ASAbhijeet Singh Software Tester | G43: Finished | H43: =VLOOKUP(B:B,Sheet1!$B$1:$I$74,8,0) -> Wordpress | I43: Done
A44: 43 | B44: Graphic Design Print | C44: Graphic Design Print | D44: =VLOOKUP(B:B,Sheet1!$B$1:$I$74,4,0) -> 08-December-2025 | E44: =VLOOKUP(B:B,Sheet1!$B$1:$I$74,5,0) -> 15-April-2026 | F44: =VLOOKUP(B:B,Sheet1!$B$1:$I$74,6,0) -> DWDeepak Web Developer | G44: Finished | H44: =VLOOKUP(B:B,Sheet1!$B$1:$I$74,8,0) -> Wordpress | I44: Done
A45: 44 | B45: Corby Motors | C45: Corby Motors | D45: =VLOOKUP(B:B,Sheet1!$B$1:$I$74,4,0) -> 23-February-2026 | E45: =VLOOKUP(B:B,Sheet1!$B$1:$I$74,5,0) -> 20-April-2026 | F45: =VLOOKUP(B:B,Sheet1!$B$1:$I$74,6,0) -> DWNWDeepak Web Developer, Nikhil Web Developer | G45: On Hold | H45: =VLOOKUP(B:B,Sheet1!$B$1:$I$74,8,0) -> Wordpress | I45: Not live , Need to get update from internal team ( UAT ) | J45: corbymotors@gmail.com | K45: Mail sent
A46: 45 | B46: Kent Wasp Control | C46: Kent Wasp Control | D46: =VLOOKUP(B:B,Sheet1!$B$1:$I$74,4,0) -> 16-March-2026 | E46: =VLOOKUP(B:B,Sheet1!$B$1:$I$74,5,0) -> 24-April-2026 | F46: =VLOOKUP(B:B,Sheet1!$B$1:$I$74,6,0) -> DWAWDeepak Web Developer, Aman Web Developer | G46: Finished | H46: =VLOOKUP(B:B,Sheet1!$B$1:$I$74,8,0) -> Wordpress | I46: Done
A47: 46 | B47: Patrick Shoes | C47: Patrick Shoes | D47: =VLOOKUP(B:B,Sheet1!$B$1:$I$74,4,0) -> 13-April-2026 | E47: =VLOOKUP(B:B,Sheet1!$B$1:$I$74,5,0) -> 24-April-2026 | F47: =VLOOKUP(B:B,Sheet1!$B$1:$I$74,6,0) -> DWVFDeepak Web Developer, Vani Frontend developer | G47: Finished | H47: =VLOOKUP(B:B,Sheet1!$B$1:$I$74,8,0) -> Custom | I47: Done
A48: 47 | B48: Adam's Painting & Decorating | C48: Adam's Painting & Decorating | D48: =VLOOKUP(B:B,Sheet1!$B$1:$I$74,4,0) -> 13-March-2026 | E48: =VLOOKUP(B:B,Sheet1!$B$1:$I$74,5,0) -> 16-May-2026 | F48: =VLOOKUP(B:B,Sheet1!$B$1:$I$74,6,0) -> +1 | G48: Finished | H48: =VLOOKUP(B:B,Sheet1!$B$1:$I$74,8,0) -> Wordpress | I48: Done
A49: 48 | B49: Allen House - FRANCHISE LANDING PAGE PROJECT | C49: Allen House - FRANCHISE LANDING PAGE PROJECT | D49: =VLOOKUP(B:B,Sheet1!$B$1:$I$74,4,0) -> 30-April-2026 | E49: =VLOOKUP(B:B,Sheet1!$B$1:$I$74,5,0) -> 16-May-2026 | F49: =VLOOKUP(B:B,Sheet1!$B$1:$I$74,6,0) -> +4 | G49: Finished | H49: =VLOOKUP(B:B,Sheet1!$B$1:$I$74,8,0) -> Custom | I49: Done
A50: 49 | B50: DRC Auto Sales | C50: DRC Auto Sales | D50: =VLOOKUP(B:B,Sheet1!$B$1:$I$74,4,0) -> 29-January-2026 | E50: =VLOOKUP(B:B,Sheet1!$B$1:$I$74,5,0) -> 26-May-2026 | F50: =VLOOKUP(B:B,Sheet1!$B$1:$I$74,6,0) -> ASNWAbhijeet Singh Software Tester, Nikhil Web Developer | G50: Finished | H50: =VLOOKUP(B:B,Sheet1!$B$1:$I$74,8,0) -> Wordpress | I50: Done
A51: 50 | B51: Solar Panel Bird Proofing Ken | C51: Solar Panel Bird Proofing Ken | D51: =VLOOKUP(B:B,Sheet1!$B$1:$I$74,4,0) -> 18-March-2026 | E51: =VLOOKUP(B:B,Sheet1!$B$1:$I$74,5,0) -> 20-April-2026 | F51: Deepak | G51: Finished | H51: =VLOOKUP(B:B,Sheet1!$B$1:$I$74,8,0) -> Wordpress | I51: Done
A52: 51 | B52: SSL | C52: SSL | D52: =VLOOKUP(B:B,Sheet1!$B$1:$I$74,4,0) -> 28-January-2026 | E52: =VLOOKUP(B:B,Sheet1!$B$1:$I$74,5,0) -> 0 | F52: =VLOOKUP(B:B,Sheet1!$B$1:$I$74,6,0) -> AWNWAman Web Developer, Nikhil Web Developer | G52: Finished | H52: =VLOOKUP(B:B,Sheet1!$B$1:$I$74,8,0) -> Shopify | I52: Done
A53: 52 | B53: iDrive Auto | C53: iDrive Auto | D53: =VLOOKUP(B:B,Sheet1!$B$1:$I$74,4,0) -> 11-December-2025 | E53: =VLOOKUP(B:B,Sheet1!$B$1:$I$74,5,0) -> 0 | F53: =VLOOKUP(B:B,Sheet1!$B$1:$I$74,6,0) -> AWAman Web Developer | G53: Finished | H53: =VLOOKUP(B:B,Sheet1!$B$1:$I$74,8,0) -> Wordpress | I53: Done
A54: 53 | B54: Optimum Global Care | C54: Optimum Global Care | D54: =VLOOKUP(B:B,Sheet1!$B$1:$I$74,4,0) -> 09-October-2025 | E54: =VLOOKUP(B:B,Sheet1!$B$1:$I$74,5,0) -> 0 | F54: =VLOOKUP(B:B,Sheet1!$B$1:$I$74,6,0) -> 0 | G54: On Hold | H54: =VLOOKUP(B:B,Sheet1!$B$1:$I$74,8,0) -> Wordpress | I54: Any update on the UAT ? From client end | J54: info@optimumglobalcare.co.uk | K54: Mail sent
A55: 54 | B55: Know & Grow Tutors | C55: Know & Grow Tutors | D55: =VLOOKUP(B:B,Sheet1!$B$1:$I$74,4,0) -> 14-October-2025 | E55: =VLOOKUP(B:B,Sheet1!$B$1:$I$74,5,0) -> 0 | F55: =VLOOKUP(B:B,Sheet1!$B$1:$I$74,6,0) -> NWNikhil Web Developer | G55: Finished | H55: =VLOOKUP(B:B,Sheet1!$B$1:$I$74,8,0) -> Wordpress | I55: Done
A56: 55 | B56: Mk Global Consultant | C56: Mk Global Consultant | D56: =VLOOKUP(B:B,Sheet1!$B$1:$I$74,4,0) -> 06-October-2025 | E56: =VLOOKUP(B:B,Sheet1!$B$1:$I$74,5,0) -> 0 | F56: =VLOOKUP(B:B,Sheet1!$B$1:$I$74,6,0) -> +2 | G56: Finished | H56: =VLOOKUP(B:B,Sheet1!$B$1:$I$74,8,0) -> Wordpress | I56: Done
A57: 56 | B57: DelaVogue Fashion | C57: DelaVogue Fashion | D57: =VLOOKUP(B:B,Sheet1!$B$1:$I$74,4,0) -> 10-October-2025 | E57: =VLOOKUP(B:B,Sheet1!$B$1:$I$74,5,0) -> 0 | F57: =VLOOKUP(B:B,Sheet1!$B$1:$I$74,6,0) -> +1 | G57: Finished | H57: =VLOOKUP(B:B,Sheet1!$B$1:$I$74,8,0) -> Wordpress | I57: Done
A58: 57 | B58: THR Gas and Solutions | C58: THR Gas and Solutions | D58: 45724 | E58: 45782 | F58: Deepak | G58: On Hold | H58: Wordpress | I58: Any update on the UAT ? From client end | J58: thrgasandheatingsolutions@yahoo.com | K58: Mail sent
A59: 58 | B59: M13 Construction | C59: M13 Construction | D59: 45723 | E59: 45745 | F59: Deepak | G59: On Hold | H59: Wordpress | I59: Any update on the UAT ? From client end | J59: naz.m13@hotmail.com | K59: Mail sent
A60: 59 | B60: Grout & Tile Sealing Service | C60: Grout & Tile Sealing Service | D60: 45847 | E60: 45869 | F60: Deepak | G60: On Hold | H60: Wordpress | I60: Any update on the UAT ? From client end | J60: info@topmodatilingservices.co.uk | K60: Mail sent
A61: 60 | B61: New Images Architects | C61: New Images Architects | D61: 45824 | E61: 45833 | F61: Deepak | G61: On Hold | H61: Wordpress | I61: Any update on the UAT ? From client end | J61: shaz.etemadi7@gmail.com | K61: Mail sent
A62: 61 | B62: Medical Device Software And Sterilization Professionals Ltd | C62: Medical Device Software And Sterilization Professionals Ltd | D62: 45930 | E62: 45954 | F62: Deepak | G62: On Hold | H62: Wordpress | I62: Any update on the UAT ? From client end | J62: office.mdsspro@gmail.com | K62: Mail sent
A63: 62 | B63: HTV Events | C63: HTV Events | D63: 45936 | E63: 45955 | F63: Deepak | G63: On Hold | H63: Wordpress | I63: Any update on the UAT ? From client end | J63: admin@htvevents.co.uk | K63: Mail sent
A64: 63 | B64: YARDX | C64: YARDX | D64: 45945 | E64: 45974 | F64: Deepak | G64: On Hold | H64: Wordpress | I64: Any update on the UAT ? From client end | J64: Mohsinhussain110@hotmail.com | K64: Mail sent
A65: 64 | B65: Graphics Design & Print | C65: Graphics Design & Print | D65: 45987 | E65: 45996 | F65: Deepak | G65: On Hold | H65: Wordpress | I65: Any update on the UAT ? From client end | J65: designs@mrsoor.co.uk | K65: Mail sent
A66: 65 | B66: London Bollards | C66: London Bollards | D66: 45994 | E66: 46006 | F66: Deepak | G66: On Hold | H66: Wordpress | I66: We want the product list for the final updates | J66: contact@londonbollards.com | K66: Mail sent
A67: 66 | B67: De'Osa Engineering | C67: De'Osa Engineering | D67: 45899 | E67: 45903 | F67: Deepak | G67: On Hold | H67: Wordpress | I67: Demo not confirmed | J67: info@deosaengineering.co.uk | K67: Mail sent
A68: 67 | B68: Tailor Made Arrangement | C68: Tailor Made Arrangement | D68: 46045 | E68: 46071 | F68: Deepak | G68: On Hold | H68: Wordpress | I68: We want the product list for the final updates | J68: NA/ | K68: Mail sent

Sheet ProjectDash
A1: FastRanking OnBoarding Project Report
D4: On Going Client Project Status Report
U5: All FastRanking Project Status Report
A6: Status | B6: Count of S.No. | R6: Status | S6: Sum of S.No.
A7: Finished | B7: 41 | R7: In Progress | S7: 431
A8: In Progress | B8: 12 | R8: Not Started | S8: 235
A9: On Hold | B9: 4 | R9: UAT | S9: 37
A10: UAT | B10: 2
R24: Project Categories | S24: Sum of S.No.
A25: Project Categories | B25: Count of S.No. | R25: Custom | S25: 124
A26: Custom | B26: 6 | R26: Inhouse | S26: 285
A27: Inhouse | B27: 2 | R27: Shopify | S27: 224
A28: Shopify | B28: 15 | R28: Wordpress | S28: 70
A29: Wordpress | B29: 36

Sheet 29th_June_Report_CP
D2: On Going Client Project Status Report
A3: Status | B3: Sum of S.No.
A4: Finished | B4: 1370
A5: In Progress | B5: 93
A6: On Hold | B6: 813
A7: UAT | B7: 2

Sheet Sheet1
A1: S.No. | B1: Project Name | C1: Customer | D1: Tags | E1: Start Date | F1: Deadline | G1: Members | H1: Status | I1: Project Categories | J1: Actions
A2: 3 | B2: CLARITY COMPARE LIMITED | C2: CLARITY COMPARE LIMITED | E2: 13-October-2025 | F2: 13-October-2025 | G2: ASAbhijeet Singh Software Tester | H2: Finished | I2: Wordpress
A3: 4 | B3: Rashid driving school | C3: Rashid driving school | E3: 31-October-2025 | F3: 31-October-2025 | G3: +1 | H3: Finished | I3: Wordpress
A4: 5 | B4: FOOTWEAR DEPOT - 1 | C4: FOOTWEAR DEPOT - 1 | E4: 11-February-2026 | F4: 13-February-2026 | G4: AWNWAman Web Developer, Nikhil Web Developer | H4: Finished | I4: Shopify
A5: 6 | B5: Best Value Auto | C5: Best Value Auto | E5: 16-October-2025 | F5: 08-April-2026 | G5: ASAbhijeet Singh Software Tester | H5: Finished | I5: Wordpress
A6: 7 | B6: CouloneStone | C6: SEO - Coulon Stone | E6: 13-February-2026 | F6: 08-April-2026 | G6: +2 | H6: Finished | I6: Wordpress
A7: 8 | B7: Sustainable Packaging Supplies Ltd | C7: Sustainable Packaging Supplies Ltd | E7: 03-October-2025 | F7: 09-April-2026 | G7: +1 | H7: Finished | I7: Wordpress
A8: 9 | B8: J2R safety | C8: J2R safety | E8: 14-October-2025 | F8: 09-April-2026 | G8: ASAbhijeet Singh Software Tester | H8: Finished | I8: Wordpress
A9: 10 | B9: EA Driving School | C9: EA Driving School | E9: 27-October-2025 | F9: 09-April-2026 | G9: ASAbhijeet Singh Software Tester | H9: Finished | I9: Wordpress
A10: 11 | B10: RRJ Design | C10: RRJ Design | E10: 24-February-2026 | F10: 09-April-2026 | G10: ASDWAbhijeet Singh Software Tester, Deepak Web Developer | H10: Finished | I10: Wordpress
A11: 12 | B11: Agid Van | C11: Agid Van | E11: 03-October-2025 | F11: 13-April-2026 | G11: ASAWAbhijeet Singh Software Tester, Aman Web Developer | H11: Finished | I11: Wordpress
A12: 13 | B12: Greyson Studios | C12: Mr. Matthew Elegbede | E12: 10-March-2026 | F12: 15-April-2026 | G12: DWDeepak Web Developer | H12: In Progress | I12: Wordpress
A13: 14 | B13: Briggs Safety Wear | C13: SEO - Briggs Safety Wear | E13: 27-March-2026 | F13: 15-April-2026 | G13: +1 | H13: In Progress | I13: Wordpress
... A26: 27 | B26: Veedux Production | C26: Veedux Production | E26: 25-October-2025 | F26: 15-April-2026 | G26: ASAbhijeet Singh Software Tester | H26: Finished | I26: Wordpress
A27: 28 | B27: Eden's Edge | C27: Eden's Edge | E27: 16-February-2026 | F27: 15-April-2026 | H27: Finished | I27: Wordpress
A28: 29 | B28: Kitchen 3D Limited | C28: Kitchen 3D Limited | E28: 17-December-2025 | F28: 15-April-2026 | G28: ASAbhijeet Singh Software Tester | H28: Finished | I28: Wordpress
A29: 30 | B29: Graphic Design Print | C29: Graphic Design Print | E29: 08-December-2025 | F29: 15-April-2026 | G29: DWDeepak Web Developer | H29: Finished | I29: Wordpress
A30: 31 | B30: Wood and Home | C30: Wood and Home | E30: 12-January-2026 | F30: 15-April-2026 | G30: ASAbhijeet Singh Software Tester | H30: Finished | I30: Wordpress
A31: 32 | B31: Qube Architects | C31: Qube Architects | E31: 19-January-2026 | F31: 15-April-2026 | H31: Finished | I31: Wordpress
A32: 33 | B32: SOS Plumbing Services | C32: SOS Plumbing Services | E32: 30-January-2026 | F32: 15-April-2026 | G32: NWNikhil Web Developer | H32: Finished | I32: Wordpress
A33: 34 | B33: Get Set Cook | C33: Get Set Cook | E33: 04-February-2026 | F33: 15-April-2026 | G33: NWNikhil Web Developer | H33: Finished | I33: Wordpress
A34: 36 | B34: RBD Driving School | C34: RBD Driving School | E34: 02-April-2026 | F34: 15-April-2026 | G34: ASDWAbhijeet Singh Software Tester, Deepak Web Developer | H34: Not Started | I34: Shopify
A35: 37 | B35: XSPEED ENGINES | C35: XSPEED ENGINES | E35: 30-January-2026 | F35: 17-April-2026 | G35: ASNWAbhijeet Singh Software Tester, Nikhil Web Developer | H35: On Hold | I35: Custom
A36: 38 | B36: Nelson News | C36: Nelson News | E36: 10-April-2026 | F36: 18-April-2026 | G36: AWAman Web Developer | H36: Finished | I36: Wordpress
A37: 39 | B37: Solar Panel Bird Proofing Ken | C37: Deepak Pachauri | E37: 18-March-2026 | F37: 20-April-2026 | G37: +1 | H37: Finished | I37: Wordpress
A38: 40 | B38: Corby Motors | C38: Corby Motors | E38: 23-February-2026 | F38: 20-April-2026 | G38: DWNWDeepak Web Developer, Nikhil Web Developer | H38: On Hold | I38: Wordpress
A39: 41 | B39: Kent Wasp Control | C39: Pallavi | E39: 16-March-2026 | F39: 24-April-2026 | G39: DWAWDeepak Web Developer, Aman Web Developer | H39: Finished | I39: Wordpress
A40: 42 | B40: Patrick Shoes | C40: Patrick Shoes | E40: 13-April-2026 | F40: 24-April-2026 | G40: DWVFDeepak Web Developer, Vani Frontend developer | H40: Finished | I40: Custom
A41: 46 | B41: Adam's Painting & Decorating | C41: Adam's Painting & Decorating | E41: 13-March-2026 | F41: 16-May-2026 | G41: +1 | H41: Finished | I41: Wordpress
A42: 47 | B42: Allen House - FRANCHISE LANDING PAGE PROJECT | C42: Allen House | E42: 30-April-2026 | F42: 16-May-2026 | G42: +4 | H42: Finished | I42: Custom
A43: 50 | B43: JEWELLERY DESIGN CENTRE LIMITED | C43: JEWELLERY DESIGN CENTRE LIMITED | E43: 16-April-2026 | F43: 20-May-2026 | G43: DWAWDeepak Web Developer, Aman Web Developer | H43: In Progress | I43: Shopify
... A64: 94 | B64: CATESBY ENGLAND | C64: CATESBY ENGLAND | E64: 21-January-2026 | F64: 31-July-2027 | G64: +2 | H64: In Progress | I64: Shopify
A65: 97 | B65: MARKETPLACE | C65: MARKETPLACE | E65: 21-January-2026 | G65: +1 | H65: In Progress | I65: Shopify
A66: 98 | B66: Nomads Trade Website | C66: Nomads Trade Website | E66: 14-October-2025 | G66: +1 | H66: In Progress | I66: Shopify
A67: 103 | B67: Stabilus | C67: Stabilus | E67: 11-December-2025 | G67: ASAWAbhijeet Singh Software Tester, Aman Web Developer | H67: Not Started | I67: Shopify
A68: 104 | B68: SSL | C68: SSL | E68: 28-January-2026 | G68: AWNWAman Web Developer, Nikhil Web Developer | H68: Finished | I68: Shopify
A69: 105 | B69: iDrive Auto | C69: iDrive Auto | E69: 11-December-2025 | G69: AWAman Web Developer | H69: Finished | I69: Wordpress
A70: 106 | B70: Optimum Global Care | C70: Optimum Global Care | E70: 09-October-2025 | H70: On Hold | I70: Wordpress
A71: 107 | B71: Know & Grow Tutors | C71: Know & Grow Tutors | E71: 14-October-2025 | G71: NWNikhil Web Developer | H71: Finished | I71: Wordpress
A72: 108 | B72: Mk Global Consultant | C72: Mk Global Consultant | E72: 06-October-2025 | G72: +2 | H72: Finished | I72: Wordpress
A73: 109 | B73: DelaVogue Fashion | C73: DelaVogue Fashion | E73: 10-October-2025 | G73: +1 | H73: Finished | I73: Wordpress
A74: 111 | B74: Space Car Executive | C74: Space Car Executive | E74: 02-April-2026 | G74: DWNWDeepak Web Developer, Nikhil Web Developer | H74: Finished | I74: Shopify

Sheet Sheet2
A1: Row Labels | B1: Sum of S.No.
A2: Backlink Checker Tool | Automated SEO Verification | B2: 13
A3: UAT | B3: 13
A4: Content Writing AI-Powered SEO Content Automation | B4: 15
A5: UAT | B5: 15
A6: Keyword Indexing Tool | Automated Rank Checking | B6: 14
A7: UAT | B7: 14
A8: Management Task | B8: 16.373626
A9: UAT | B9: 16.373626
A10: AI Agent - Call History Downloader — Ameyo | DMA Phase 3 | B10: 8
A11: In Progress | B11: 8
A12: AI Automation — Ameyo Call Details Report Downloader | B12: 7
A13: In Progress | B13: 7
... A38: Grand Total | B38: 187.02198

Sheet All Sales
A1: Group | B1: Deals | C1: Category | D1: BUSINESS NAME | E1: Title | F1: Fulla Name | G1: Designation | H1: Phone | I1: Mobile | J1: Email | K1: Website | L1: Sale Status | M1: Service | N1: Techstack | O1: Cost | P1: Sale Date | Q1: Business Type | R1: DSR | S1: Lead Created Date | T1: Lead ID | U1: Lead Type | V1: BDR | W1: Payment Frequency | X1: Payment Type
A2: BABYPINK | B2: 1 | C2: Beauty, Hair & Wellness | D2: BABYPINK | K2: No Website | L2: Sale Processed | M2: Web Dev | N2: Custom | O2: £250.00 | P2: 44927 | Q2: New | R2: Other | S2: 44927 | U2: Fresh | V2: Other | W2: One-off - Partial | X2: One-off
A3: ANDY PARK PROMOTIONS | B3: 1 | C3: Entertainment Agency | D3: ANDY PARK PROMOTIONS | E3: Mr | F3: Andy Park | G3: Owner | H3: 1228818182 | I3: 7368361254 | J3: andypark8181@gmail.com | K3: https://www.andyparkpromotions.co.uk/ | L3: Sale Processed | M3: Digital Marketing | N3: SMO | O3: £250.00 | P3: 45007 | Q3: New | R3: Akram | S3: 44999 | T3: 203 | U3: Fresh | V3: Other | W3: Monthly | X3: Recurring
A4: LOCKMAN247 | B4: 1 | C4: Security & Safety | D4: LOCKMAN247 | E4: Mr | F4: Lee Bennett | G4: Director | H4: 1270342247 | I4: 7730582469 | J4: info@lockman247.co.uk | K4: https://lockman247.co.uk/ | L4: Sale Processed | M4: Web Dev | N4: Wordpress | O4: £300.00 | P4: 45029 | Q4: New | R4: Akram | S4: 45016 | T4: 204 | U4: Fresh | V4: Other | W4: One-off - Partial | X4: One-off
A5: LOCKMAN247 | B5: 2 | C5: Security & Safety | D5: LOCKMAN247 | E5: Mr | F5: Lee Bennett | G5: Director | H5: 1270342247 | I5: 7730582469 | J5: info@lockman247.co.uk | K5: https://lockman247.co.uk/ | L5: Sale Processed | M5: Digital Marketing | N5: SEO | O5: £250.00 | P5: 45029 | Q5: Cross-Sell | R5: Akram | S5: 45016 | T5: 204 | U5: Fresh | V5: Other | W5: Monthly | X5: Recurring
A6: METALMASTER PROMOTIONS UK LTD | B6: 1 | C6: Specialist Trades | D6: METALMASTER PROMOTIONS UK LTD | E6: Mr | F6: Paul Sammut | G6: Director | H6: 2086705042 | I6: 7986003426 | J6: info4u2@metalmaster.co.uk | K6: https://www.metalmaster.co.uk/ | L6: Sale Processed | M6: Digital Marketing | N6: SMO | O6: £100.00 | P6: 45048 | Q6: New | R6: Akram | S6: 45035 | T6: 252 | U6: Fresh | V6: Other | W6: Monthly | X6: Recurring
A7: DW STORE | B7: 1 | C7: Clothing | D7: D W Store | E7: Mr | F7: Dudley Washington | G7: Director | I7: 7774831154 | J7: alexlawson660@gmail.com | K7: No Website | L7: Sale Processed | M7: Web Dev | N7: Wordpress | O7: £400.00 | P7: 45083 | Q7: New | R7: Akram | S7: 45254 | T7: 351 | U7: Fresh | V7: Other | W7: One-off - Partial | X7: One-off
A8: Coulon Stone Limited | B8: 1 | C8: Tiling, Bathrooms & Kitchens | D8: Coulon Stone Limited | E8: Mr | F8: Simon Coulon | G8: Director | H8: 1494484333 | I8: 7971863682 | J8: simon@coulonstone.com | K8: https://coulonstone.com/ | L8: Sale Processed | M8: Web Dev | N8: Wordpress | O8: £300.00 | P8: 45106 | Q8: New | R8: Akram | S8: 45069 | T8: 205 | U8: Fresh | V8: Other | W8: One-off - Partial | X8: One-off
A9: Coulon Stone Limited | B9: 2 | C9: Tiling, Bathrooms & Kitchens | D9: Coulon Stone Limited | E9: Mr | F9: Simon Coulon | G9: Director | H9: 1494484333 | I9: 7971863682 | J9: simon@coulonstone.com | K9: https://coulonstone.com/ | L9: Sale Processed | M9: Digital Marketing | N9: SEO | O9: £250.00 | P9: 45106 | Q9: Cross-Sell | R9: Akram | S9: 45069 | T9: 205 | U9: Fresh | V9: Other | W9: Monthly | X9: Recurring
A10: ALAN LAM | B10: 1 | C10: Health & Supplements | D10: ALAN LAM | E10: Mr | F10: Alan Lam | G10: Owner | H10: 2086532751 | I10: 7947000568 | J10: admin@alan-lam.co.uk | K10: https://www.alan-lam.co.uk/ | L10: Sale Processed | M10: Web Dev | N10: Wordpress | O10: £300.00 | P10: 45112 | Q10: New | R10: Akram | S10: 45110 | T10: 207 | U10: Fresh | V10: Akram | W10: One-off - Partial | X10: One-off
A11: 108 BUILDERS LIMITED | B11: 1 | C11: Builders & General Construction | D11: 108 BUILDERS LIMITED | E11: Mr | F11: Bogdan Tomaszewicz | G11: Director | I11: 7722242035 | J11: bogdan@108builders.co.uk | K11: https://108builders.co.uk/ | L11: Sale Processed | M11: Web Dev | N11: Custom | O11: £300.00 | P11: 45149 | Q11: New | R11: Akram | S11: 45161 | T11: 31 | U11: Fresh | V11: Akram | W11: One-off - Partial | X11: One-off
A12: M - CABS LYMEREGIS | B12: 1 | C12: Taxi, Chauffeur & Transport | D12: M - CABS LYMEREGIS | E12: Mr | F12: Christian Joseph | G12: Owner | H12: 1297442222 | I12: 7801996414 | J12: vonmerowing@gmail.com | K12: https://mcabslymeregis.co.uk/ | L12: Sale Processed | M12: Web Dev | N12: Wordpress | O12: £250.00 | P12: 45166 | Q12: New | R12: Akram | S12: 45161 | T12: 28 | U12: Fresh | V12: Other | W12: One-off - Partial | X12: One-off
A13: Superhouse Group | B13: 1 | C13: Footwear | D13: NOTHWEST TERRITORY | E13: Mr | F13: Sharooq Imam | G13: Manager | H13: 1327703841 | I13: 7876366810 | J13: sharooq@patrickshoes.co.uk | K13: https://northwestterritory.co.uk/ | L13: Sale Processed | M13: Web Dev | N13: Shopify | O13: £400.00 | P13: 45177 | Q13: New | R13: Akram | S13: 45078 | T13: 253 | U13: Fresh | V13: Akram | W13: One-off - Partial | X13: One-off
A14: PAUL BAILEY HOME EXTENSIONS | B14: 1 | C14: Builders & General Construction | D14: PAUL BAILEY HOME EXTENSIONS | E14: Mr | F14: Paul Bailey | G14: Owner | H14: 1277532991 | I14: 7545307419 | J14: Info@paulbailey.info | K14: https://loftconversionsessex.co.uk/ | L14: Sale Processed | M14: Digital Marketing | N14: SEO | O14: £150.00 | P14: 45196 | Q14: New | R14: Akram | S14: 45197 | T14: 18 | U14: Fresh | V14: Other | W14: Monthly | X14: Recurring
A15: MASSEY PROPERTY | B15: 1 | C15: Property & Real Estate | D15: MASSEY PROPERTY | E15: Mrs | F15: Joanna Martin | G15: Owner | H15: 1273727278 | J15: jo.blaise@masseyproperty.com | K15: https://www.masseyproperty.com/ | L15: Sale Processed | M15: Digital Marketing | N15: SEO | O15: £400.00 | P15: 45197 | Q15: New | R15: Akram | S15: 45098 | T15: 115 | U15: Fresh | V15: Other | W15: Monthly | X15: Recurring
A16: LB TAXI | B16: 1 | C16: Taxi, Chauffeur & Transport | D16: L B Taxis Ltd | E16: Mr | F16: Mohammed Belal Ahmed | G16: Director | H16: 1525464646 | I16: 7846373112 | J16: belal-mhd@hotmail.co.uk | K16: https://lbtaxi.co.uk/ | L16: Sale Processed | M16: Web Dev | N16: Wordpress | O16: £300.00 | P16: 45209 | Q16: New | R16: Akram | S16: 45264 | T16: 137 | U16: Fresh | V16: Other | W16: One-off - Partial | X16: One-off
A17: XTRA SENSE | B17: 1 | C17: Security & Safety | D17: XTRA SENSE | E17: Mr | F17: Peter Hutcheson | G17: Owner | H17: 140443366 | I17: 140443366 | J17: security@xtra-sense.co.uk | K17: https://www.xtra-sense.co.uk/ | L17: Sale Processed | M17: Web Dev | N17: Wordpress | O17: £250.00 | P17: 45215 | Q17: New | R17: Akram | S17: 45215 | T17: 117 | U17: Fresh | V17: Other | W17: One-off - Partial | X17: One-off
A18: AHIMSA LONDON LIMITED | B18: 1 | C18: Jewellery | D18: LABMADE DIAMOND | E18: Mr | F18: Nerav Mehta | G18: Director | I18: 7824345308 | J18: ahimsalondon@gmail.com | K18: https://www.labmadediamonds.co.uk/ | L18: Sale Processed | M18: Web Dev | N18: Wordpress | O18: £3,000.00 | P18: 45222 | Q18: New | R18: Other | S18: 45296 | T18: 126 | U18: Fresh | V18: Other | W18: One-off - Partial | X18: One-off
A19: AHIMSA LONDON LIMITED | B19: 2 | C19: Jewellery | D19: LABMADE DIAMOND | E19: Mr | F19: Nerav Mehta | G19: Director | I19: 7824345308 | J19: ahimsalondon@gmail.com | K19: https://www.labmadediamonds.co.uk/ | L19: Sale Processed | M19: Digital Marketing | N19: SEO | O19: £799.00 | P19: 45222 | Q19: Cross-Sell | R19: Akram | S19: 45296 | T19: 126 | U19: Fresh | V19: Other | W19: Monthly | X19: Recurring
A20: Plan And Build London Ltd | B20: 1 | C20: Education & Training | D20: REVISE WITH ME | E20: Mr | F20: Tomi Adebayo | G20: Director | I20: 7961161810 | J20: tomi@planandbuild.net | K20: https://revisewithme.com/ | L20: Sale Processed | M20: Web Dev | N20: Custom | O20: £8,500.00 | P20: 45223 | Q20: New | R20: Akram | S20: 45223 | T20: 92 | U20: Fresh | V20: Other | W20: One-off - Partial | X20: One-off
A21: M & A STRUCTURAL DESIGN | B21: 1 | C21: Engineering & Structural | D21: M&A STRUCTURAL DESIGN SERVICES LIMITTED | E21: Mr | F21: Ahmed Yasser | G21: Director | H21: 1865600067 | J21: info@masds.co.uk | K21: https://masds.co.uk/ | L21: Sale Processed | M21: Web Dev | N21: Wordpress | O21: £300.00 | P21: 45224 | Q21: New | R21: Akram | S21: 45566 | U21: Fresh | V21: Other | W21: One-off - Partial | X21: One-off
A22: BEST SIZZLER | B22: 1 | C22: Food & Hospitality | D22: BEST SIZZLER LIMITED | E22: Mr | F22: Arbaaz Ahmed | I22: 7447907544 | J22: arbaz007o1@gmail.com | K22: No Website | L22: Sale Processed | M22: Web Dev | N22: Custom | O22: £1,000.00 | P22: 45245 | Q22: New | R22: Akram | S22: 45566 | T22: FRID002128 | U22: Fresh | V22: Tamal | W22: One-off - Partial | X22: One-off
A23: KAD ELECTRICALS | B23: 1 | C23: Electrical Services | D23: KAD ELECTRICIANS LTD | E23: Mr | F23: Kastro Pashku | G23: Director | I23: 7429540950 | J23: info@kadelectricians.co.uk | K23: https://kadelectricians.co.uk/ | L23: Sale Processed | M23: Web Dev | N23: Wordpress | O23: £250.00 | P23: 45250 | Q23: New | R23: Akram | S23: 45566 | T23: FRID002129 | U23: Fresh | V23: Other | W23: One-off - Partial | X23: One-off
A24: DA ROWLEY | B24: 1 | C24: Builders & General Construction | D24: D A ROWLEY LIMITED | E24: Mr | F24: Andrew Rowley | G24: Director | I24: 7976762990 | J24: arowley07@aol.com | K24: http://www.darowley.com/ | L24: Sale Processed | M24: Web Dev | N24: Wordpress | O24: £250.00 | P24: 45259 | Q24: New | R24: Akram | S24: 45566 | T24: FRID002130 | U24: Fresh | V24: Other | W24: One-off - Partial | X24: One-off
A25: PATCHITT JOINERY | B25: 1 | C25: Carpentry & Joinery | D25: A AND C R PATCHITT | E25: Mr | F25: Samuel Patchitt | G25: Owner | H25: 1159390011 | I25: 7932578092 | J25: sam@patchitt-joinery.co.uk | K25: https://patchitt-joinery.co.uk/ | L25: Sale Processed | M25: Web Dev | N25: Wordpress | O25: £250.00 | P25: 45260 | Q25: New | R25: Akram | S25: 45566 | T25: FRID002131 | U25: Fresh | V25: Other | W25: One-off - Partial | X25: One-off
A26: 10 PLUS ONE STORE | B26: 1 | C26: Retail & E-Commerce | D26: 10 PLUS ONE STORE | E26: Mr | F26: Kamal Jeet Singh | G26: Director | I26: 7366146695 | J26: 11elevenmotion@gmail.com | K26: https://10plusonestore.co.uk/ | L26: Sale Processed | M26: Web Dev | N26: Wordpress | O26: £1,200.00 | P26: 45278 | Q26: New | R26: Akram | S26: 45566 | T26: FRID002132 | U26: Fresh | V26: Tamal | W26: One-off - Partial | X26: One-off
A27: SPLENDENT TILE & PAINT LTD | B27: 1 | C27: Tiling, Bathrooms & Kitchens | D27: SPLENDENT TILE & PAINT LTD | E27: Mr | F27: Sohan Singh | G27: Director | I27: 7438564925 | J27: splendent1984@gmail.com | K27: https://splendenttile.co.uk/ | L27: Sale Processed | M27: Digital Marketing | N27: SEO | O27: £150.00 | P27: 45313 | Q27: New | R27: Aryan | S27: 45632 | T27: FRID002948 | U27: Fresh | V27: Deepak | W27: Monthly | X27: Recurring
A28: Superhouse Group | B28: 4 | C28: Footwear | D28: AMEN SHOES - PATRICK SHOES LIMITED | E28: Mr | F28: Noain Bakshi | G28: Director | H28: 1327703841 | J28: noain@patrickshoes.co.uk | K28: https://amenshoesuk.co.uk/ | L28: Sale Processed | M28: Web Dev | N28: Shopify | O28: £400.00 | P28: 45322 | Q28: New | R28: Akram | S28: 45566 | T28: FRID002115 | U28: Reference | V28: Akram | W28: One-off - Partial | X28: One-off
A29: Superhouse Group | B29: 5 | C29: Footwear | D29: AMEN SHOES - PATRICK SHOES LIMITED | E29: Mr | F29: Noain Bakshi | G29: Director | H29: 1327703841 | J29: noain@patrickshoes.co.uk | K29: https://amenshoesuk.co.uk/ | L29: Sale Processed | M29: Digital Marketing | N29: SEO | O29: £200.00 | P29: 45322 | Q29: Cross-Sell | R29: Akram | S29: 45566 | T29: FRID002115 | U29: Reference | V29: Akram | W29: Monthly | X29: Recurring
A30: SHOREDITCH INN LIMITED | B30: 1 | C30: Food & Hospitality | D30: SHOREDITCH INN LIMITED | E30: Mr | F30: Praveen Kishore | G30: Director | I30: 7830114154 | J30: raj@shoreditchinn.com | K30: https://shoreditchinn.com/ | L30: Sale Processed | M30: Digital Marketing | N30: SEO | O30: £300.00 | P30: 45334 | Q30: New | R30: Akram | S30: 45566 | T30: FRID002136 | U30: Reference | V30: Tamal | W30: Monthly | X30: Recurring
A31: SCOTTAXI | B31: 1 | C31: Taxi, Chauffeur & Transport | D31: SCOT TAXI | E31: Mr | F31: Nikolay Kostov | G31: Owner | I31: 7928086205 | J31: booking@scottaxi.com | K31: https://scottaxi.com/ | L31: Sale Processed | M31: Web Dev | N31: Wordpress | O31: £300.00 | P31: 45385 | Q31: New | R31: Akram | S31: 45566 | T31: FRID002137 | U31: Fresh | V31: Other | W31: One-off - Partial | X31: One-off
A32: SCOTTAXI | B32: 2 | C32: Taxi, Chauffeur & Transport | D32: SCOT TAXI | E32: Mr | F32: Nikolay Kostov | G32: Owner | I32: 7928086205 | J32: booking@scottaxi.com | K32: https://scottaxi.com/ | L32: Sale Processed | M32: Digital Marketing | N32: SEO | O32: £150.00 | P32: 45385 | Q32: Cross-Sell | R32: Akram | S32: 45566 | T32: FRID002137 | U32: Fresh | V32: Other | W32: Monthly | X32: Recurring
A33: Superhouse Group | B33: 6 | C33: Footwear | D33: SILVER STREET - SUPERHOUSE (UK) LIMITED | E33: Mr | F33: Akbar Waris | K33: https://www.silverstreetlondon.co.uk/ | L33: Sale Processed | M33: Web Dev | N33: Shopify | O33: £400.00 | P33: 45390 | Q33: New | R33: Akram | S33: 45566 | U33: Reference | V33: Akram | W33: One-off - Partial | X33: One-off
A34: Superhouse Group | B34: 7 | C34: Footwear | D34: SILVER STREET - SUPERHOUSE (UK) LIMITED | E34: Mr | F34: Akbar Waris | K34: https://www.silverstreetlondon.co.uk/ | L34: Sale Processed | M34: Digital Marketing | N34: SEO | O34: £200.00 | P34: 45390 | Q34: Cross-Sell | R34: Akram | S34: 45566 | U34: Reference | V34: Akram | W34: Monthly | X34: Recurring
A35: Superhouse Group | B35: 8 | C35: Footwear | D35: BRIGGS INDUSTRIAL FOOTWEAR LIMITED | E35: Mr | F35: Akbar Waris | K35: https://briggssafetywear.com/ | L35: Sale Processed | M35: Web Dev | N35: Shopify | O35: £600.00 | P35: 45412 | Q35: New | R35: Akram | S35: 45566 | T35: FRID002169 | U35: Reference | V35: Akram | W35: One-off - Partial | X35: One-off
A36: Superhouse Group | B36: 9 | C36: Footwear | D36: BRIGGS INDUSTRIAL FOOTWEAR LIMITED | E36: Mr | F36: Akbar Waris | K36: https://briggssafetywear.com/ | L36: Sale Processed | M36: Digital Marketing | N36: SEO | O36: £200.00 | P36: 45412 | Q36: Cross-Sell | R36: Akram | S36: 45566 | T36: FRID002169 | U36: Reference | V36: Akram | W36: Monthly | X36: Recurring
A37: MILTON MENSWEAR LIMITED | B37: 1 | C37: Clothing | D37: MILTON MENSWEAR LIMITED | E37: Mr | F37: Jeremy John Lawson | G37: Director | H37: 1202292895 | I37: 7779777112 | J37: sales@alfa-menswear.com | K37: https://www.alfa-menswear.com/ | L37: Sale Processed | M37: Web Dev | N37: Custom | O37: £150.00 | P37: 45415 | Q37: New | R37: Akram | S37: 45572 | T37: FRID002174 | U37: Fresh | V37: Other | W37: One-off - Partial | X37: One-off
A38: Superhouse Group | B38: 10 | C38: Footwear | D38: SADDLER ACCESSORIES LTD | E38: Mr | F38: Gavin Watson | G38: Manager | H38: 1327221187 | I38: 7951635585 | J38: gavin@saddler-accessories.com | K38: https://saddler-accessories.com/ | L38: Sale Processed | M38: Web Dev | N38: Shopify | O38: £600.00 | P38: 45433 | Q38: New | R38: Akram | S38: 45483 | T38: FRID000202 | U38: Fresh | V38: Akram | W38: One-off - Partial | X38: One-off
A39: Superhouse Group | B39: 11 | C39: Footwear | D39: SADDLER ACCESSORIES LTD | E39: Mr | F39: Gavin Watson | G39: Manager | H39: 1327221187 | I39: 7951635585 | J39: gavin@saddler-accessories.com | K39: https://saddler-accessories.com/ | L39: Sale Processed | M39: Digital Marketing | N39: SEO | O39: £200.00 | P39: 45433 | Q39: Cross-Sell | R39: Akram | S39: 45483 | T39: FRID000202 | U39: Fresh | V39: Akram | W39: Monthly | X39: Recurring
A40: SOS PLUMBING SERVICES LTD | B40: 1 | C40: Plumbing, Heating & Gas | D40: SOS PLUMBING SERVICES LTD | E40: Mr | F40: Claudiu Stefan Rosca | G40: Director | I40: 7932439650 | J40: plumbingservices83@gmail.com | K40: https://sosplumberservices.co.uk/ | L40: Sale Processed | M40: Web Dev | N40: Wordpress | O40: £250.00 | P40: 45477 | Q40: New | R40: Akram | S40: 45468 | T40: FRID000077 | U40: Fresh | V40: Ibrahim | W40: One-off - Partial | X40: One-off | Y40: 241137 | AA40: £300.00 | AB40: Paid
A41: SOS PLUMBING SERVICES LTD | B41: 2 | C41: Plumbing, Heating & Gas | D41: SOS PLUMBING SERVICES LTD | E41: Mr | F41: Claudiu Stefan Rosca | G41: Director | I41: 7932439650 | J41: plumbingservices83@gmail.com | K41: https://sosplumberservices.co.uk/ | L41: Sale Processed | M41: Digital Marketing | N41: SEO | O41: £250.00 | P41: 45477 | Q41: Cross-Sell | R41: Akram | S41: 45468 | T41: FRID000077 | U41: Fresh | V41: Ibrahim | W41: Monthly | X41: Recurring | Y41: 241147 | AA41: £300.00 | AB41: Paid
A42: SADGURU KRUPA LIMITED | B42: 1 | C42: Retail & E-Commerce | D42: SADGURU KRUPA LIMITED | E42: Mr | F42: Yogeshkumar Patel | G42: Director | H42: 2085429448 | I42: 7823555955 | J42: nelson.news17@hotmail.com | K42: https://mertonparkpostoffice.co.uk/ | L42: Sale Processed | M42: Web Dev | N42: Custom | O42: £400.00 | P42: 45488 | Q42: New | R42: Akram | S42: 45485 | T42: FRID000221 | U42: Fresh | V42: Abhinav | W42: One-off - Partial | X42: One-off
A43: JOHN FRENCH T/A RED RADIO - FAST RANKING | B43: 1 | C43: Electrical Services | D43: JOHN FRENCH T/A RED RADIO - FAST RANKING | E43: Mr | F43: John French | G43: Owner | H43: 1582481114 | J43: john@red-radio.co.uk | K43: https://www.red-radio.co.uk/ | L43: Sale Processed | M43: Web Dev | N43: Wordpress | O43: £800.00 | P43: 45512 | Q43: New | R43: Akram | S43: 45576 | T43: FRID002206 | U43: Fresh | V43: Akram | W43: One-off - Partial | X43: One-off
A44: CARUNIVERSAL LTD | B44: 1 | C44: Automotive & Vehicle Services | D44: CARUNIVERSAL LTD | E44: Mr | F44: Veaceslav Anestiade | G44: Director | I44: 7436304422 | J44: caruniversalltd.office@gmail.com | K44: No Website | L44: Sale Processed | M44: Web Dev | N44: Wordpress | O44: £562.50 | P44: 45518 | Q44: New | R44: Akram | S44: 45490 | T44: FRID000547 | U44: Fresh | V44: Naveen | W44: One-off - Partial | X44: One-off
A45: EURO GLAZING LTD | B45: 1 | C45: Glazing & Windows | D45: EURO GLAZING LTD | E45: Mr | F45: Rana Khan | G45: Director | I45: 7475214014 | J45: euroglazingwindows@gmail.com | K45: https://www.euro-glazing.uk/ | L45: Sale Processed | M45: Web Dev | N45: Wordpress | O45: £300.00 | P45: 45541 | Q45: New | R45: Akram | S45: 45518 | T45: FRID000115 | U45: Fresh | V45: Naveen | W45: One-off - Partial | X45: One-off
A46: ROTHERHAM ROAD RUNNER LTD | B46: 1 | C46: Taxi, Chauffeur & Transport | D46: ROTHERHAM ROAD RUNNER LTD | E46: Mr | F46: Faisal Syed | G46: Director | I46: 7964932829 | J46: rotherhamroadrunner@yahoo.com | K46: No Website | L46: Sale Processed | M46: Web Dev | N46: Wordpress | O46: £250.00 | P46: 45556 | Q46: New | R46: Akram | S46: 45535 | T46: FRID001762 | U46: Fresh | V46: Franklin | W46: One-off - Partial | X46: One-off
A47: Superhouse Group | B47: 2 | C47: Footwear | D47: NOTHWEST TERRITORY | E47: Mr | F47: Noain Bakshi | G47: Director | H47: 1327703841 | J47: noain@patrickshoes.co.uk | K47: https://northwestterritory.co.uk/ | L47: Sale Processed | M47: Digital Marketing | N47: SEO | O47: £200.00 | P47: 45566 | Q47: Cross-Sell | R47: Akram | S47: 45305 | W47: Monthly | X47: Recurring
A48: COUNSELLING THERAPY LONDON | B48: 1 | C48: Consulting & Business Services | D48: COUNSELLING THERAPY LONDON | E48: Ms | F48: Dhanesh Sakaria | I48: 7593023563 | J48: info@counsellingtherapylondon.co.uk | K48: https://counsellingtherapylondon.co.uk/ | L48: Sale Processed | M48: Web Dev | N48: Wordpress | O48: £250.00 | P48: 45568 | Q48: New | R48: Akram | S48: 45513 | T48: FRID001435 | U48: Fresh | V48: Ankita | W48: One-off - Partial | X48: One-off
A49: Superhouse Group | B49: 12 | C49: Education & Training | D49: ALLENHOUSE - (APS + DPS) | E49: Mr | F49: Sanjay Kapoor | G49: Director | J49: director@knowledgehouse.org.in | K49: https://allenhouseschools.com/ | L49: Sale Processed | M49: Web Dev | N49: Custom | O49: £6,500.00 | P49: 45586 | Q49: Cross-Sell | R49: Akram | S49: 45586 | U49: Reference | V49: Akram | W49: One-off - Partial | X49: One-off
A50: Coulon Stone Limited | B50: 3 | C50: Tiling, Bathrooms & Kitchens | D50: Coulon Stone Limited | E50: Mr | F50: Simon Coulon | G50: Director | H50: 1494484333 | I50: 7971863682 | J50: simon@coulonstone.com | K50: https://coulonstone.com/ | L50: Sale Processed | M50: Production Support & Maintenance | N50: Hosting & Maintenance | O50: £125.00 | P50: 45597 | Q50: Cross-Sell | R50: Akram | S50: 45069 | T50: 205 | U50: Fresh | V50: Other | W50: Annually | X50: Recurring | Y50: Need to send
A51: DRC AUTO SALES LTD | B51: 1 | C51: Automotive & Vehicle Services | D51: DRC AUTO SALES LTD | E51: Mrs | F51: Violeta Badan | G51: Director | I51: 7799175108 | J51: office@drcautosales.co.uk | K51: https://www.drcautosales.co.uk/ | L51: Sale Processed | M51: Web Dev | N51: Wordpress | O51: £450.00 | P51: 45601 | Q51: New | R51: Akram | S51: 45586 | T51: FRID002285 | U51: Fresh | V51: Ankita | W51: One-off - Partial | X51: One-off
A52: TOP MODA TILING SERVICES | B52: 1 | C52: Tiling, Bathrooms & Kitchens | D52: TOP MODA TILING SERVICES | E52: Mr | F52: Remon Daly | I52: 7816440947 | J52: info@topmodatilingservices.co.uk | K52: https://topmodatilingservices.co.uk/ | L52: Sale Processed | M52: Digital Marketing | N52: SEO | O52: £125.00 | P52: 45604 | Q52: New | R52: Aryan | S52: 45601 | T52: FRID002376 | U52: Fresh | V52: Anurag | W52: Monthly | X52: Recurring
A53: HIRE SUPPORT LIMITED | B53: 1 | C53: Builders & General Construction | D53: HIRE SUPPORT LIMITED | E53: Mr | F53: Haney Abulebdeh | I53: 7785460003 | J53: hire.s95@aol.com | K53: No Website | L53: Sale Processed | M53: Web Dev | N53: Wordpress | O53: £250.00 | P53: 45610 | Q53: New | R53: Akram | S53: 45572 | T53: FRID002170 | U53: Fresh | V53: Ankita | W53: One-off - Partial | X53: One-off
A54: BLU PLUMBING | B54: 1 | C54: Plumbing, Heating & Gas | D54: BLU PLUMBING LIMITED | E54: Mr | F54: Ivan Kondov | G54: Director | I54: 7475056553 | J54: info@bluplumbing.co.uk | K54: https://bluplumbing.co.uk/ | L54: Sale Processed | M54: Web Dev | N54: Wordpress | O54: £250.00 | P54: 45617 | Q54: New | R54: Aryan | S54: 45611 | T54: FRID000286 | U54: Fresh | V54: Anurag | W54: One-off - Partial | X54: One-off
A55: CHESHIRE TOOL AND PRESSING COMPANY LIMITED | B55: 1 | C55: Specialist Trades | D55: CHESHIRE TOOL AND PRESSING COMPANY LIMITED | E55: Mr | F55: Phillip Carr | H55: 1457873479 | I55: 7733397831 | J55: phil.carr@ctcpressings.com | K55: https://ctc-cheshiretool.co.uk/ | L55: Sale Processed | M55: Web Dev | N55: Wordpress | O55: £300.00 | P55: 45622 | Q55: New | R55: Akram | S55: 45484 | T55: FRID000210 | U55: Fresh | V55: Shivank | W55: One-off - Partial | X55: One-off
A56: ARTEM PAINTERS | B56: 1 | C56: Painting & Decorating | D56: ARTEM PAINTERS | E56: Mr | F56: Mr. Perrie . | I56: 7391277028 | J56: perrie@artempainters.com | K56: https://www.artempainters.com/ | L56: Sale Processed | M56: Web Dev | N56: Custom | O56: £330.00 | P56: 45623 | Q56: New | R56: Aryan | S56: 45615 | T56: FRID002505 | U56: Fresh | V56: Naveen | W56: One-off - Partial | X56: One-off
A57: OLYMPUS MOBILE TYRE FITTING | B57: 1 | C57: Automotive & Vehicle Services | D57: OLYMPUS MOBILE TYRE FITTING | E57: Mr | F57: Antonio | G57: Owner | I57: 7426059209 | J57: hello@olympustyres.co.uk | K57: https://olympusmobiletyrefitting.co.uk/ | L57: Sale Processed | M57: Web Dev | N57: Wordpress | O57: £250.00 | P57: 45625 | Q57: New | R57: Akram | S57: 45618 | T57: FRID002550 | U57: Fresh | V57: Dhruv | W57: One-off - Partial | X57: One-off
A58: CAMERABOSS PHOTOGRAPHY UK | B58: 1 | C58: Photography & Media | D58: CAMERABOSS PHOTOGRAPHY UK | E58: Mr | F58: John Lekan | G58: Owner | I58: 7823714814 | J58: camerabossphotos@gmail.com | K58: https://www.cameraboss.co.uk/ | L58: Sale Processed | M58: Digital Marketing | N58: SEO | O58: £140.00 | P58: 45629 | Q58: New | R58: Aryan | S58: 45615 | T58: FRID002501 | U58: Fresh | V58: Yashwin | W58: Monthly | X58: Recurring
A59: KITES FOR SCHOOL | B59: 1 | C59: Education & Training | D59: KITES FOR SCHOOL | E59: Mrs | F59: Karen Gamble | H59: 1308456274 | I59: 7984016401 | J59: kites@kitesforschools.co.uk | K59: https://kitesforschools.co.uk/ | L59: Sale Processed | M59: Web Dev | N59: Custom | O59: £300.00 | P59: 45629 | Q59: New | R59: Aryan | S59: 45626 | T59: FRID002550 | U59: Fresh | V59: Dhruv | W59: One-off - Partial | X59: One-off
A60: NEWHAM SCHOOL OF MOTORING | B60: 1 | C60: Driving Schools & Instructors | D60: NEWHAM SCHOOL OF MOTORING | E60: Mr | F60: Mohammed | G60: Owner | I60: 7897668516 | J60: newhamschoolofmotoring@gmail.com | K60: https://newhamschoolofmotoring.co.uk/ | L60: Sale Processed | M60: Web Dev | N60: Wordpress | O60: £150.00 | P60: 45636 | Q60: New | R60: Aryan | S60: 45635 | T60: FRID002795 | U60: Fresh | V60: Dhruv | W60: One-off - Partial | X60: One-off
A61: TAROT READING BY AKSHATA K | B61: 1 | C61: Consulting & Business Services | D61: TAROT READING BY AKSHATA K | E61: Ms | F61: Akshata Kamble | I61: 7935151568 | J61: akshatak.ak@gmail.com | K61: No Website | L61: Sale Processed | M61: Digital Marketing | N61: SEO | O61: £110.00 | P61: 45638 | Q61: New | R61: Aryan | S61: 45552 | T61: FRID001958 | U61: Fresh | V61: Naveen | W61: Monthly | X61: Recurring
A62: OPTIMUM GLOBAL | B62: 1 | C62: Education & Training | D62: OPTIMUM GLOBAL LINKS | E62: Mr | F62: Sodiq | G62: Owner | I62: 7448487279 | J62: jaydas2001@yahoo.co.uk | K62: https://www.optimumgloballinks.co.uk/ | L62: Sale Processed | M62: Web Dev | N62: Wordpress | O62: £125.00 | P62: 45644 | Q62: New | R62: Aryan | S62: 45629 | T62: FRID002665 | U62: Fresh | V62: Ankita | W62: One-off - Partial | X62: One-off
A63: AVIN ACCOUNTANTS LTD | B63: 1 | C63: Financial & Accounting | D63: AVIN ACCOUNTANTS LTD | E63: Mr | F63: Vinodkumar Valand | I63: 7877747928 | J63: vinod@avinaccountants.com | K63: https://avinaccountants.com/ | L63: Sale Processed | M63: Web Dev | N63: Wordpress | O63: £500.00 | P63: 45657 | Q63: New | R63: Akram | S63: 45561 | T63: FRID002069 | U63: Fresh | V63: Kaveer | W63: One-off - Partial | X63: One-off
A64: TOP MODA TILING SERVICES | B64: 2 | C64: Tiling, Bathrooms & Kitchens | D64: TOP MODA TILING SERVICES | E64: Mr | F64: Remon Daly | I64: 7816440947 | J64: info@topmodatilingservices.co.uk | K64: https://topmodatilingservices.co.uk/ | L64: Sale Processed | M64: Web Dev | N64: Wordpress | O64: £250.00 | P64: 45667 | Q64: Cross-Sell | R64: Aryan | S64: 45601 | T64: FRID002376 | U64: Fresh | V64: Anurag | W64: One-off - Partial | X64: One-off
A65: BRITISH QUILTING | B65: 1 | C65: Clothing | D65: BRITISH QUILTING | E65: Mr | F65: Mustafa Gunc | I65: 7710131416 | J65: mustafagunc@yahoo.com | K65: https://britishquilting.com/ | L65: Sale Processed | M65: Web Dev | N65: Wordpress | O65: £1,000.00 | P65: 45674 | Q65: New | R65: Aryan | S65: 45673 | T65: FRID003459 | U65: Fresh | V65: Deepak | W65: One-off - Partial | X65: One-off
A66: FLY INTERNATIONAL TRADING LTD | B66: 1 | C66: Retail & E-Commerce | D66: FLY INTERNATIONAL TRADING LTD | E66: Mr | F66: Wei Yang | I66: 7411112207 | J66: flytrading@gmail.com | K66: https://flybedding.com/ | L66: Sale Processed | M66: Web Dev | N66: Wordpress | O66: £420.00 | P66: 45677 | Q66: New | R66: Aryan | S66: 45670 | T66: FRID003418 | U66: Fresh | V66: Ankita | W66: One-off - Partial | X66: One-off
A67: OLYMPUS MOBILE TYRE FITTING | B67: 2 | C67: Automotive & Vehicle Services | D67: OLYMPUS MOBILE TYRE FITTING | E67: Mr | F67: Antonio | G67: Owner | I67: 7426059209 | J67: hello@olympustyres.co.uk | K67: https://olympusmobiletyrefitting.co.uk/ | L67: Sale Processed | M67: Digital Marketing | N67: SEO | O67: £300.00 | P67: 45678 | Q67: Cross-Sell | R67: Akram | S67: 45618 | T67: FRID002550 | U67: Fresh | V67: Dhruv | W67: Monthly | X67: Recurring
A68: RAE FINANCIAL ADVISORY SERVICES LTD | B68: 2 | C68: Financial & Accounting | D68: RAE FINANCIAL ADVISORY SERVICES LTD | E68: Mr | F68: Ramzy Abu Eda | I68: 7957656773 | J68: ramzy@raefinancialservices.co.uk | K68: https://raefinancialservices.co.uk/ | L68: Sale Processed | M68: Web Dev | N68: Wordpress | O68: £334.00 | P68: 45685 | Q68: Cross-Sell | R68: Aryan | S68: 45643 | T68: FRID003240 | U68: Fresh | V68: Bhumi | W68: One-off - Partial | X68: One-off
A69: SOFIYA DESIGNS LIMITED | B69: 1 | C69: Architecture & Design | D69: SOFIYA DESIGNS LIMITED | E69: Ms | F69: Sofiya Burnusuz | G69: Director | I69: 7910781802 | J69: sofiya@sofiyadesigns.co.uk | K69: https://sofiyadesigns.co.uk/ | L69: Sale Processed | M69: Web Dev | N69: Wordpress | O69: £500.00 | P69: 45686 | Q69: New | R69: Akram | S69: 45681 | T69: FRID003545 | U69: Fresh | V69: Franklin | W69: One-off - Partial | X69: One-off
A70: BURAQ ELECTRIC | B70: 1 | C70: Electrical Services | D70: BURAQ ELECTRIC | E70: Mr | F70: Habib Khan | I70: 7899714173 | J70: info@buraqelectic.co.uk | K70: https://buraqelectric.co.uk/ | L70: Sale Processed | M70: Digital Marketing | N70: SEO | O70: £125.00 | P70: 45687 | Q70: New | R70: Aryan | S70: 45681 | T70: FRID003551 | U70: Fresh | V70: Rohit | W70: Monthly | X70: Recurring
A71: RAFIQ CATERING | B71: 1 | C71: Food & Hospitality | D71: RAFIQ CATERING | E71: Mr | F71: Rafiq Patel | I71: 7878385876 | J71: info@rafiqcatering.com | K71: https://www.rafiqcatering.com/ | L71: Sale Processed | M71: Web Dev | N71: Wordpress | O71: £300.00 | P71: 45688 | Q71: New | R71: Aryan | S71: 45685 | T71: FRID003635 | U71: Fresh | V71: Franklin | W71: One-off - Partial | X71: One-off
A72: SECURITY PROTECTION LTD | B72: 1 | C72: Security & Safety | D72: SECURITY PROTECTION LTD | E72: Mr | F72: Harprtte Nazwan | I72: 7787144558 | J72: info.spro.ltd@gmail.com | K72: https://securityprotectionltd.co.uk/ | L72: Sale Processed | M72: Web Dev | N72: Wordpress | O72: £200.00 | P72: 45688 | Q72: New | R72: Aryan | S72: 45688 | T72: FRID003663 | U72: Fresh | V72: Mamta | W72: One-off - Partial | X72: One-off
A73: TNO LIMITED | B73: 1 | C73: Plumbing, Heating & Gas | D73: TNO LIMITED | E73: Mr | F73: Oleg Angheluta | G73: Director | I73: 7848890841 | J73: tno_limited@yahoo.com | K73: No Website | L73: Sale Processed | M73: Web Dev | N73: Wordpress | O73: £300.00 | P73: 45692 | Q73: New | R73: Aryan | S73: 45665 | T73: FRID003218 | U73: Fresh | V73: Shone | W73: One-off - Partial | X73: One-off
A74: TAROT READING BY AKSHATA K | B74: 2 | C74: Consulting & Business Services | D74: TAROT READING BY AKSHATA K | E74: Ms | F74: Akshata Kamble | I74: 7935151568 | J74: akshatak.ak@gmail.com | K74: No Website | L74: Sale Processed | M74: Digital Marketing | N74: SEO | O74: £125.00 | P74: 45694 | Q74: Cross-Sell | R74: Aryan | S74: 45552 | T74: FRID001958 | U74: Fresh | V74: Naveen | W74: Monthly | X74: Recurring
A75: TAROT READING BY AKSHATA K | B75: 3 | C75: Consulting & Business Services | D75: TAROT READING BY AKSHATA K | E75: Ms | F75: Akshata Kamble | I75: 7935151568 | J75: akshatak.ak@gmail.com | K75: No Website | L75: Sale Processed | M75: Digital Marketing | N75: SEO | O75: £82.00 | P75: 45694 | Q75: Cross-Sell | R75: Aryan | S75: 45552 | T75: FRID001958 | U75: Fresh | V75: Naveen | W75: Monthly | X75: Recurring
A76: KING SOUTHERN SECURITY | B76: 1 | C76: Security & Safety | D76: KING SOUTHERN SECURITY | E76: Mr | F76: Duzgun Cifci | I76: 7403003022 | J76: INFO@KGSSECURITY.CO.UK | K76: No Website | L76: Sale Processed | M76: Web Dev | N76: Wordpress | O76: £334.00 | P76: 45699 | Q76: New | R76: Aryan | S76: 45691 | T76: FRID003680 | U76: Fresh | V76: Rohit | W76: One-off - Partial | X76: One-off
A77: DAG METAL WORKS | B77: 1 | C77: Specialist Trades | D77: DAG METAL WORKS | E77: Mr | F77: Murat Dag | I77: 7735437949 | J77: dagmetalwork@gmail.com | K77: https://dagmetalworks.co.uk/ | L77: Sale Processed | M77: Web Dev | N77: Wordpress | O77: £334.00 | P77: 45700 | Q77: New | R77: Aryan | S77: 45699 | T77: FRID002970 | U77: Fresh | V77: Anurag | W77: One-off - Partial | X77: One-off
A78: EAGLE PROPERTY | B78: 1 | C78: Property & Real Estate | D78: EAGLE PROPERTY | K78: No Website | L78: Sale Processed | M78: Web Dev | N78: Wordpress | O78: £417.00 | P78: 45700 | Q78: New | R78: Aryan | S78: 45700 | W78: One-off - Partial | X78: One-off
A79: HMO HORIZON | B79: 1 | C79: Plumbing, Heating & Gas | D79: HMO HORIZON | E79: Mr | F79: Idris Zia | G79: Owner | I79: 7872076460 | J79: idris@hmohorizon.co.uk | K79: https://hmohorizon.co.uk/ | L79: Sale Processed | M79: Digital Marketing | N79: SEO | O79: £168.00 | P79: 45700 | Q79: New | R79: Aryan | S79: 45694 | T79: FRID003728 | U79: Fresh | V79: Mamta | W79: Monthly | X79: Recurring | Y79: 241316 | Z79: 45700 | AA79: £200.00 | AB79: Paid
A80: WOODANDHOME | B80: 1 | C80: Carpentry & Joinery | D80: WOODANDHOME | E80: Mr | F80: Przzemek | I80: 7798652923 | J80: office@woodandhome.co.uk | K80: https://woodandhome.co.uk/ | L80: Sale Processed | M80: Digital Marketing | N80: SEO | O80: £168.00 | P80: 45701 | Q80: New | R80: Aryan | S80: 45699 | T80: FRID003787 | U80: Fresh | V80: Shone | W80: Monthly | X80: Recurring
A81: ALLELECTRIX DOMESTIC APPLIANCES SALES & REPAIRS | B81: 1 | C81: General Retail & Stores | D81: ALLELECTRIX DOMESTIC APPLIANCES SALES & REPAIRS | E81: Mr | F81: Donovan Webley | I81: 7817764944 | J81: pilotwebley@me.com | K81: https://allelectrixwebley.co.uk/ | L81: Sale Processed | M81: Web Dev | N81: Wordpress | O81: £633.33 | P81: 45705 | Q81: New | R81: Aryan | S81: 45701 | T81: FRID003814 | U81: Fresh | V81: Rohit Gambhir | W81: One-off - Partial | X81: One-off
A82: BATHROOMS LONDON LIMITED | B82: 1 | C82: Tiling, Bathrooms & Kitchens | D82: BATHROOMS LONDON LIMITED | E82: Mr | F82: Khyyam Nabil Potia | H82: 2045467850 | I82: 7932995964 | J82: hello@bathroomslondonltd.com | K82: https://www.bathroomslondonltd.com/ | L82: Sale Processed | M82: Web Dev | N82: Wordpress | O82: £500.00 | P82: 45705 | Q82: New | R82: Akram | S82: 45628 | T82: FRID002648 | U82: Fresh | V82: Shone | W82: One-off - Partial | X82: One-off | Y82: 245705
A83: ROOFING XPERTS LTD | B83: 1 | C83: Roofing & Guttering | D83: ROOFING XPERTS LTD | E83: Mr | F83: Jatinder Pal Singh | I83: 7526559378 | J83: Info@roofingxperts.co.uk | K83: https://roofingxperts.co.uk/ | L83: Sale Processed | M83: Web Dev | N83: Wordpress | O83: £210.00 | P83: 45705 | Q83: New | R83: Aryan | S83: 45678 | T83: FRID003493 | U83: Fresh | V83: Anurag | W83: One-off - Partial | X83: One-off
A84: Superhouse Group | B84: 13 | C84: Clothing | D84: NOMADS CLOTHING LTD | E84: Mr | F84: Akbar Waris | K84: https://nomadsclothing.com/ | L84: Sale Processed | M84: Web Dev | N84: Shopify | O84: £599.00 | P84: 45707 | Q84: Cross-Sell | R84: Akram | S84: 45707 | U84: Reference | W84: One-off - Partial | X84: One-off
A85: THR GAS & HEATING SOLUTIONS | B85: 1 | C85: Plumbing, Heating & Gas | D85: THR GAS & HEATING SOLUTIONS | E85: Mr | F85: Anwarul Kabir | G85: Owner | I85: 7939689137 | J85: thrgasnheatingsolutions@yahoo.com | K85: https://thrgasnheatingsolutions.co.uk/ | L85: Sale Processed | M85: Web Dev | N85: Wordpress | O85: £250.00 | P85: 45709 | Q85: New | R85: Aryan | S85: 45635 | T85: FRID001941 | U85: Fresh | V85: Rohit | W85: One-off - Partial | X85: One-off | Y85: 241332 | AA85: £100.00 | AB85: Paid
A86: BEST VALUE AUTOS | B86: 1 | C86: Automotive & Vehicle Services | D86: BEST VALUE AUTOS | E86: Mr | F86: Kamal Kapadia | G86: Owner | I86: 7727624725 | J86: contactbestvalueauto@gmail.com | K86: https://bestvalueauto.co.uk/ | L86: Sale Processed | M86: Web Dev | N86: Wordpress | O86: £300.00 | P86: 45714 | Q86: New | R86: Varun | S86: 45712 | T86: FRID003542 | U86: Fresh | V86: Anurag | W86: One-off - Partial | X86: One-off | Y86: 241336
A87: VIP CHAUFFEURS SERVICE LONDON LTD | B87: 1 | C87: Taxi, Chauffeur & Transport | D87: VIP CHAUFFEURS SERVICE LONDON LTD | E87: Mr | F87: Vladimirs Kuncevics | I87: 7921462700 | J87: contact@vvkcontractorsltd.com | K87: https://vipchauffeursservice.co.uk/ | L87: Sale Processed | M87: Digital Marketing | N87: SEO | O87: £300.00 | P87: 45714 | Q87: New | R87: Varun | S87: 45699 | T87: FRID003796 | U87: Fresh | V87: Shone | W87: Monthly | X87: Recurring
A88: ARI TRANS LTD | B88: 1 | C88: Logistics | D88: ARI TRANS LTD | E88: Mr | F88: Ovidiu Socel | G88: Director | I88: 7392256442 | J88: ovidiu_socel@icloud.com | K88: https://www.road-van-finder.co.uk/ | L88: Sale Processed | M88: Web Dev | N88: Wordpress | O88: £300.00 | P88: 45718 | Q88: New | R88: Aryan | S88: 45701 | T88: FRID003377 | U88: Fresh | V88: Yashwin | W88: One-off - Partial | X88: One-off | Y88: 241348
A89: Decorator In London | B89: 1 | C89: Painting & Decorating | D89: Decorator In London | E89: Mr | F89: Andrew Nicholson | I89: 7983404611 | J89: info@decoratorinlondon.co.uk | K89: No Website | L89: Sale Processed | M89: Web Dev | N89: Wordpress | O89: £300.00 | P89: 45720 | Q89: New | R89: Aryan | S89: 45560 | T89: FRID002059 | U89: Fresh | V89: Anurag | W89: One-off - Partial | X89: One-off | Y89: 241349
A90: FINE FINISH DECORATIVE | B90: 1 | C90: Painting & Decorating | D90: FINE FINISH DECORATIVE | K90: No Website | L90: Sale Processed | M90: Web Dev | N90: Wordpress | O90: £300.00 | P90: 45720 | Q90: New | R90: Aryan | S90: 45720 | W90: One-off - Partial | X90: One-off
A91: MS & MR CLEANING | B91: 1 | C91: Cleaning & Maintenance | D91: MS & MR CLEANING | E91: Ms | F91: Lazime Shehu | G91: Owner | I91: 7832974550 | J91: msandmrcleaning@gmail.com | K91: https://msandmrcleaning.co.uk/ | L91: Sale Processed | M91: Web Dev | N91: Wordpress | O91: £300.00 | P91: 45721 | Q91: New | R91: Aryan | S91: 45696 | T91: FRID003768 | U91: Fresh | V91: Franklin | W91: One-off - Partial | X91: One-off
A92: BRITISH QUILTING | B92: 2 | C92: Clothing | D92: BRITISH QUILTING | E92: Mr | F92: Mustafa Gunc | I92: 7710131416 | J92: mustafagunc@yahoo.com | K92: https://britishquilting.com/ | L92: Sale Processed | M92: Web Dev | N92: Custom | O92: £3,000.00 | P92: 45728 | Q92: Cross-Sell | R92: Akram | S92: 45673 | T92: FRID003459 | U92: Fresh | V92: Deepak | W92: One-off - Partial | X92: One-off | Y92: 241451/241609
A93: Superhouse Group | B93: 15 | C93: Footwear | D93: CATESBY | E93: Mr | F93: Noain Bakshi | G93: Director | H93: 1327703841 | J93: noain@testtest.com | K93: https://catesbyengland.com/ | L93: Sale Processed | M93: Web Dev | N93: Shopify | O93: £395.00 | P93: 45729 | Q93: New | R93: Akram | S93: 45734 | T93: FRID004152 | U93: Reference | V93: Akram | W93: One-off - Partial | X93: One-off | Y93: 241077
A94: VARSITY MUSIC | B94: 1 | C94: Entertainment Agency | D94: VARSITY MUSIC | E94: Mr | F94: Dhruv Patel | I94: 7950843633 | J94: info@varsityaudiovisuals.com | K94: No Website | L94: Sale Processed | M94: Web Dev | N94: Wordpress | O94: £300.00 | P94: 45729 | Q94: New | R94: Aryan | S94: 45705 | T94: FRID003850 | U94: Fresh | V94: Yashwin | W94: One-off - Partial | X94: One-off
A95: BE STUDIO INTERIORS AND ARCHITECTURE | B95: 1 | C95: Architecture & Design | D95: BE STUDIO INTERIORS AND ARCHITECTURE | E95: Mr | F95: Bilal Tatar | G95: Owner | I95: 7578603970 | J95: contact@be-studio.co.uk | K95: https://www.be-studio.co.uk/ | L95: Sale Processed | M95: Digital Marketing | N95: SEO | O95: £125.00 | P95: 45734 | Q95: New | R95: Aryan | S95: 45721 | T95: FRID004042 | U95: Fresh | V95: Yashwin | W95: Monthly | X95: Recurring | Y95: 241363
A96: CAR THEFT PROTECT | B96: 1 | C96: Security & Safety | D96: CAR THEFT PROTECT | E96: Mr | F96: Jack Sparrow | I96: 7460694437 | J96: office@cartheftprotect.co.uk | K96: https://cartheftprotect.co.uk/ | L96: Sale Processed | M96: Web Dev | N96: Wordpress | O96: £334.00 | P96: 45736 | Q96: New | R96: Aryan | S96: 45735 | T96: FRID004188 | U96: Fresh | V96: Aakash | W96: One-off - Partial | X96: One-off | Y96: 241372
A97: DRC AUTO SALES LTD | B97: 2 | C97: Automotive & Vehicle Services | D97: DRC AUTO SALES LTD | E97: Mrs | F97: Violeta Badan | G97: Director | I97: 7799175108 | J97: office@drcautosales.co.uk | K97: https://drcautosales.co.uk/ | L97: Sale Processed | M97: Digital Marketing | N97: SEO | O97: £200.00 | P97: 45736 | Q97: Cross-Sell | R97: Akram | S97: 45586 | T97: FRID002285 | U97: Fresh | V97: Ankita | W97: Monthly | X97: Recurring
A98: KN DRIVING SCHOOL | B98: 1 | C98: Driving Schools & Instructors | D98: KN DRIVING SCHOOL | E98: Mr | F98: Khalil | G98: Owner | I98: 7882716603 | J98: kan_25_naz@yahoo.co.uk | K98: https://kndriving.co.uk/ | L98: Sale Processed | M98: Web Dev | N98: Wordpress | O98: £209.00 | P98: 45740 | Q98: New | R98: Aryan | S98: 46103 | T98: FRID004245 | U98: Fresh | V98: Anurag | W98: One-off - Partial | X98: One-off
A99: LEAPS DRIVING SCHOOL | B99: 1 | C99: Driving Schools & Instructors | D99: LEAPS DRIVING SCHOOL | E99: Mrs | F99: Shahnaz Nasir | G99: Owner | I99: 7903254150 | J99: leapsdrivingschool@gmail.com | K99: https://leapsdrivingschool.co.uk/ | L99: Sale Processed | M99: Web Dev | N99: Wordpress | O99: £300.00 | P99: 45743 | Q99: New | R99: Aryan | S99: 45661 | T99: FRID003364 | U99: Fresh | V99: Anurag | W99: One-off - Partial | X99: One-off
A100: P PLUS P ARCHITECTS | B100: 1 | C100: Architecture & Design | D100: P PLUS P ARCHITECTS | E100: Mr | F100: Michele Picoraro | G100: Owner | I100: 7876063418 | J100: info@pplusparchitects.com | K100: https://pplusparchitects.com/ | L100: Sale Processed | M100: Digital Marketing | N100: SEO | O100: £125.00 | P100: 45747 | Q100: New | R100: Aryan | S100: 45733 | T100: FRID004140 | U100: Fresh | V100: Shone | W100: Monthly | X100: Recurring
...
